Mine/prbs_edge_shaper.v
`timescale 1ns / 1ps
//////////////////////////////////////////////////////////////////////////////////
// 模块名称: prbs_edge_shaper
// 功能描述: 将1位PRBS信号整形为多位带斜坡的信号
//////////////////////////////////////////////////////////////////////////////////

module prbs_edge_shaper (
    input wire          dac_clk,                  // 主DAC时钟，例如 625MHz
    input wire          reset_n,                  // 同步低有效复位
    input wire          prbs_bit_out,             // 1位原始PRBS序列 (来自 prbs_core_lfsr)
    input wire          lfsr_clk_enable,          // PRBS移位使能 (指示 prbs_bit_out 可能变化)
    input wire [7:0]    prbs_edge_time_config_reg,// 边沿过渡DAC周期数 (Nedge_cycles)
    
    output reg  [15:0]  shaped_prbs_data,         // 16位整形后的PRBS数据
    output wire [1:0]   edge_state_dbg,           // 输出当前状态(调试用)
    output wire [7:0]   edge_counter_dbg          // 输出边沿计数器(调试用)
);

// 参数定义
parameter OUTPUT_WIDTH = 16;               // 输出位宽
parameter DAC_MAX = 16'h7FFF;              // 最大输出值 (32767)
parameter DAC_MIN = 16'h0000;              // 最小输出值 (0)

// 边沿状态机
localparam S_STEADY_LOW  = 2'b00;
localparam S_RISING_EDGE = 2'b01;
localparam S_STEADY_HIGH = 2'b10;
localparam S_FALLING_EDGE= 2'b11;

// 内部寄存器
reg [1:0] current_state, next_state;
reg [7:0] edge_counter;          // 计数边沿过渡周期
reg [15:0] current_dac_value;    // 当前DAC输出值
reg [15:0] step_size;            // 每步的数字增量/减量
reg prbs_bit_prev;               // 前一个PRBS位值

// 输出调试信号
assign edge_state_dbg = current_state;
assign edge_counter_dbg = edge_counter;

// PRBS边沿检测
always @(posedge dac_clk or negedge reset_n) begin
    if (!reset_n) begin
        prbs_bit_prev <= 1'b0;
    end else if (lfsr_clk_enable) begin
        prbs_bit_prev <= prbs_bit_out;
    end
end

wire prbs_rising_edge = lfsr_clk_enable && (prbs_bit_out && !prbs_bit_prev);
wire prbs_falling_edge = lfsr_clk_enable && (!prbs_bit_out && prbs_bit_prev);

// 计算步长 - 使用移位代替除法以节省资源
always @(*) begin
    if (prbs_edge_time_config_reg == 8'd0) begin
        step_size = DAC_MAX;  // 设置为最大值，实现瞬时跳变
    end else if (prbs_edge_time_config_reg == 8'd1) begin
        step_size = DAC_MAX;  // 只需1个周期，直接跳到最大值
    end else if (prbs_edge_time_config_reg == 8'd2) begin
        step_size = DAC_MAX >> 1;  // 最大值的一半
    end else if (prbs_edge_time_config_reg == 8'd4) begin
        step_size = DAC_MAX >> 2;  // 最大值的四分之一
    end else if (prbs_edge_time_config_reg == 8'd8) begin
        step_size = DAC_MAX >> 3;  // 最大值的八分之一
    end else if (prbs_edge_time_config_reg == 8'd16) begin
        step_size = DAC_MAX >> 4;  // 最大值的十六分之一
    end else if (prbs_edge_time_config_reg == 8'd32) begin
        step_size = DAC_MAX >> 5;  // 最大值的三十二分之一
    end else if (prbs_edge_time_config_reg == 8'd64) begin
        step_size = DAC_MAX >> 6;  // 最大值的六十四分之一
    end else if (prbs_edge_time_config_reg == 8'd128) begin
        step_size = DAC_MAX >> 7;  // 最大值的一百二十八分之一
    end else begin
        // 对于非2的幂次，使用近似值
        step_size = (DAC_MAX + (prbs_edge_time_config_reg >> 1)) / prbs_edge_time_config_reg;
    end
end

// 状态机和计数器
always @(posedge dac_clk or negedge reset_n) begin
    if (!reset_n) begin
        current_state <= S_STEADY_LOW;
        edge_counter <= 8'h0;
        current_dac_value <= DAC_MIN;
        shaped_prbs_data <= DAC_MIN;
    end else begin
        current_state <= next_state;
        
        // 更新DAC值和计数器
        case (current_state)
            S_STEADY_LOW: begin
                current_dac_value <= DAC_MIN;
                edge_counter <= 8'h0;
            end
            
            S_RISING_EDGE: begin
                edge_counter <= edge_counter + 8'h1;
                
                // 防止溢出
                if (current_dac_value + step_size > DAC_MAX || edge_counter >= prbs_edge_time_config_reg - 1) begin
                    current_dac_value <= DAC_MAX;
                end else begin
                    current_dac_value <= current_dac_value + step_size;
                end
            end
            
            S_STEADY_HIGH: begin
                current_dac_value <= DAC_MAX;
                edge_counter <= 8'h0;
            end
            
            S_FALLING_EDGE: begin
                edge_counter <= edge_counter + 8'h1;
                
                // 防止下溢
                if (current_dac_value < step_size || edge_counter >= prbs_edge_time_config_reg - 1) begin
                    current_dac_value <= DAC_MIN;
                end else begin
                    current_dac_value <= current_dac_value - step_size;
                end
            end
        endcase
        
        // 更新输出
        shaped_prbs_data <= current_dac_value;
    end
end

// 状态转换逻辑
always @(*) begin
    next_state = current_state; // 默认保持当前状态
    
    case (current_state)
        S_STEADY_LOW: begin
            // 当检测到上升沿或PRBS为高时进入上升边沿状态
            if (lfsr_clk_enable && prbs_bit_out == 1'b1) 
                next_state = S_RISING_EDGE;
        end
        
        S_RISING_EDGE: begin
            // 完成边沿过渡
            if (edge_counter >= prbs_edge_time_config_reg - 1) begin
                // 检查是否需要立即开始下降
                if (lfsr_clk_enable && prbs_bit_out == 1'b0)
                    next_state = S_FALLING_EDGE;
                else
                    next_state = S_STEADY_HIGH;
            end
        end
        
        S_STEADY_HIGH: begin
            // 当检测到下降沿或PRBS为低时进入下降边沿状态
            if (lfsr_clk_enable && prbs_bit_out == 1'b0)
                next_state = S_FALLING_EDGE;
        end
        
        S_FALLING_EDGE: begin
            // 完成边沿过渡
            if (edge_counter >= prbs_edge_time_config_reg - 1) begin
                // 检查是否需要立即开始上升
                if (lfsr_clk_enable && prbs_bit_out == 1'b1)
                    next_state = S_RISING_EDGE;
                else
                    next_state = S_STEADY_LOW;
            end
        end
    endcase
end

endmodule

Mine/prbs_edge_shaper_tb.v
`timescale 1ns / 1ps
//////////////////////////////////////////////////////////////////////////////////
// 模块名称: prbs_edge_shaper_tb
// 功能描述: PRBS边沿整形模块的测试台
//////////////////////////////////////////////////////////////////////////////////

module prbs_edge_shaper_tb();

    // 测试参数
    parameter CLK_PERIOD = 1.6; // 625MHz的时钟周期 (1.6ns)
    parameter SIM_TIME = 10000; // 仿真时间 (ns)
    
    // 时钟和复位
    reg dac_clk;
    reg reset_n;
    
    // 输入信号
    reg prbs_bit_out;            // 模拟PRBS输出位
    reg lfsr_clk_enable;         // LFSR时钟使能
    reg [7:0] prbs_edge_time_config_reg; // 边沿过渡配置
    
    // 输出信号
    wire [15:0] shaped_prbs_data;    // 整形后的输出数据
    wire [1:0] edge_state_dbg;       // 状态机状态
    wire [7:0] edge_counter_dbg;     // 边沿计数器
    
    // 实例化被测模块
    prbs_edge_shaper uut (
        .dac_clk(dac_clk),
        .reset_n(reset_n),
        .prbs_bit_out(prbs_bit_out),
        .lfsr_clk_enable(lfsr_clk_enable),
        .prbs_edge_time_config_reg(prbs_edge_time_config_reg),
        .shaped_prbs_data(shaped_prbs_data),
        .edge_state_dbg(edge_state_dbg),
        .edge_counter_dbg(edge_counter_dbg)
    );
    
    // 时钟生成
    initial begin
        dac_clk = 0;
        forever #(CLK_PERIOD/2) dac_clk = ~dac_clk;
    end
    
    // 低速PRBS时钟使能生成 (以10MHz速率模拟PRBS)
    reg [5:0] prbs_clk_div;
    always @(posedge dac_clk or negedge reset_n) begin
        if (!reset_n) begin
            prbs_clk_div <= 0;
            lfsr_clk_enable <= 0;
        end else begin
            prbs_clk_div <= prbs_clk_div + 1;
            lfsr_clk_enable <= (prbs_clk_div == 0) ? 1'b1 : 1'b0; // 625MHz/64 ≈ 10MHz
        end
    end
    
    // 测试序列
    initial begin
        // 初始化信号
        reset_n = 0;
        prbs_bit_out = 0;
        prbs_edge_time_config_reg = 8'd16; // 16个时钟周期的边沿过渡时间
        
        // 复位释放
        #100;
        reset_n = 1;
        #100;
        
        // 测试用例1: 简单的方波模式
        repeat (5) begin
            // 产生高电平
            @(posedge lfsr_clk_enable);
            prbs_bit_out = 1'b1;
            
            // 保持高电平一段时间
            repeat (5) @(posedge lfsr_clk_enable);
            
            // 产生低电平
            @(posedge lfsr_clk_enable);
            prbs_bit_out = 1'b0;
            
            // 保持低电平一段时间
            repeat (5) @(posedge lfsr_clk_enable);
        end
        
        // 测试用例2: 快速切换
        prbs_edge_time_config_reg = 8'd8; // 更短的边沿过渡时间
        repeat (10) begin
            @(posedge lfsr_clk_enable);
            prbs_bit_out = ~prbs_bit_out; // 每个PRBS时钟周期翻转
        end
        
        // 测试用例3: 更长的边沿过渡时间
        prbs_edge_time_config_reg = 8'd32;
        repeat (3) begin
            @(posedge lfsr_clk_enable);
            prbs_bit_out = 1'b1;
            repeat (10) @(posedge lfsr_clk_enable);
            prbs_bit_out = 1'b0;
            repeat (10) @(posedge lfsr_clk_enable);
        end
        
        // 测试用例4: 伪随机序列
        prbs_edge_time_config_reg = 8'd16;
        repeat (30) begin
            @(posedge lfsr_clk_enable);
            prbs_bit_out = $random; // 随机生成0或1
        end
        
        // 结束仿真
        #1000;
        $display("仿真完成!");
        $finish;
    end
    
    // 波形生成
    initial begin
        $dumpfile("edge_shaper_sim.vcd");
        $dumpvars(0, prbs_edge_shaper_tb);
    end
    
    // 状态机状态的ASCII文本表示
    reg [8*20:1] state_name;
    always @(*) begin
        case (edge_state_dbg)
            2'b00: state_name = "STEADY_LOW";
            2'b01: state_name = "RISING_EDGE";
            2'b10: state_name = "STEADY_HIGH";
            2'b11: state_name = "FALLING_EDGE";
            default: state_name = "UNKNOWN";
        endcase
    end
    
    // 监视输出
    initial begin
        $monitor("时间=%t, PRBS位=%b, 整形输出=%d, 状态=%s, 计数器=%d", 
                 $time, prbs_bit_out, shaped_prbs_data, state_name, edge_counter_dbg);
    end

endmodule

Mine/edge_shaper_sim.vcd
$date
	Tue Jun  3 16:46:05 2025
$end
$version
	Icarus Verilog
$end
$timescale
	1ps
$end
$scope module prbs_edge_shaper_tb $end
$var wire 16 ! shaped_prbs_data [15:0] $end
$var wire 2 " edge_state_dbg [1:0] $end
$var wire 8 # edge_counter_dbg [7:0] $end
$var real 1 $ CLK_PERIOD $end
$var parameter 32 % SIM_TIME $end
$var reg 1 & dac_clk $end
$var reg 1 ' lfsr_clk_enable $end
$var reg 1 ( prbs_bit_out $end
$var reg 6 ) prbs_clk_div [5:0] $end
$var reg 8 * prbs_edge_time_config_reg [7:0] $end
$var reg 1 + reset_n $end
$var reg 160 , state_name [160:1] $end
$scope module uut $end
$var wire 1 & dac_clk $end
$var wire 8 - edge_counter_dbg [7:0] $end
$var wire 2 . edge_state_dbg [1:0] $end
$var wire 1 ' lfsr_clk_enable $end
$var wire 1 ( prbs_bit_out $end
$var wire 8 / prbs_edge_time_config_reg [7:0] $end
$var wire 1 0 prbs_falling_edge $end
$var wire 1 1 prbs_rising_edge $end
$var wire 1 + reset_n $end
$var parameter 16 2 DAC_MAX $end
$var parameter 16 3 DAC_MIN $end
$var parameter 32 4 OUTPUT_WIDTH $end
$var parameter 2 5 S_FALLING_EDGE $end
$var parameter 2 6 S_RISING_EDGE $end
$var parameter 2 7 S_STEADY_HIGH $end
$var parameter 2 8 S_STEADY_LOW $end
$var reg 16 9 current_dac_value [15:0] $end
$var reg 2 : current_state [1:0] $end
$var reg 8 ; edge_counter [7:0] $end
$var reg 2 < next_state [1:0] $end
$var reg 1 = prbs_bit_prev $end
$var reg 16 > shaped_prbs_data [15:0] $end
$var reg 16 ? step_size [15:0] $end
$upscope $end
$upscope $end
$enddefinitions $end
$comment Show the parameter values. $end
$dumpall
b0 8
b10 7
b1 6
b11 5
b10000 4
b0 3
b111111111111111 2
b10011100010000 %
r1.6 $
$end
#0
$dumpvars
b11111111111 ?
b0 >
0=
b0 <
b0 ;
b0 :
b0 9
01
00
b10000 /
b0 .
b0 -
b1010011010101000100010101000001010001000101100101011111010011000100111101010111 ,
0+
b10000 *
b0 )
0(
0'
0&
b0 #
b0 "
b0 !
$end
#800
1&
#1600
0&
#2400
1&
#3200
0&
#4000
1&
#4800
0&
#5600
1&
#6400
0&
#7200
1&
#8000
0&
#8800
1&
#9600
0&
#10400
1&
#11200
0&
#12000
1&
#12800
0&
#13600
1&
#14400
0&
#15200
1&
#16000
0&
#16800
1&
#17600
0&
#18400
1&
#19200
0&
#20000
1&
#20800
0&
#21600
1&
#22400
0&
#23200
1&
#24000
0&
#24800
1&
#25600
0&
#26400
1&
#27200
0&
#28000
1&
#28800
0&
#29600
1&
#30400
0&
#31200
1&
#32000
0&
#32800
1&
#33600
0&
#34400
1&
#35200
0&
#36000
1&
#36800
0&
#37600
1&
#38400
0&
#39200
1&
#40000
0&
#40800
1&
#41600
0&
#42400
1&
#43200
0&
#44000
1&
#44800
0&
#45600
1&
#46400
0&
#47200
1&
#48000
0&
#48800
1&
#49600
0&
#50400
1&
#51200
0&
#52000
1&
#52800
0&
#53600
1&
#54400
0&
#55200
1&
#56000
0&
#56800
1&
#57600
0&
#58400
1&
#59200
0&
#60000
1&
#60800
0&
#61600
1&
#62400
0&
#63200
1&
#64000
0&
#64800
1&
#65600
0&
#66400
1&
#67200
0&
#68000
1&
#68800
0&
#69600
1&
#70400
0&
#71200
1&
#72000
0&
#72800
1&
#73600
0&
#74400
1&
#75200
0&
#76000
1&
#76800
0&
#77600
1&
#78400
0&
#79200
1&
#80000
0&
#80800
1&
#81600
0&
#82400
1&
#83200
0&
#84000
1&
#84800
0&
#85600
1&
#86400
0&
#87200
1&
#88000
0&
#88800
1&
#89600
0&
#90400
1&
#91200
0&
#92000
1&
#92800
0&
#93600
1&
#94400
0&
#95200
1&
#96000
0&
#96800
1&
#97600
0&
#98400
1&
#99200
0&
#100000
1'
b1 )
1&
1+
#100800
0&
#101600
0'
b10 )
1&
#102400
0&
#103200
b11 )
1&
#104000
0&
#104800
b100 )
1&
#105600
0&
#106400
b101 )
1&
#107200
0&
#108000
b110 )
1&
#108800
0&
#109600
b111 )
1&
#110400
0&
#111200
b1000 )
1&
#112000
0&
#112800
b1001 )
1&
#113600
0&
#114400
b1010 )
1&
#115200
0&
#116000
b1011 )
1&
#116800
0&
#117600
b1100 )
1&
#118400
0&
#119200
b1101 )
1&
#120000
0&
#120800
b1110 )
1&
#121600
0&
#122400
b1111 )
1&
#123200
0&
#124000
b10000 )
1&
#124800
0&
#125600
b10001 )
1&
#126400
0&
#127200
b10010 )
1&
#128000
0&
#128800
b10011 )
1&
#129600
0&
#130400
b10100 )
1&
#131200
0&
#132000
b10101 )
1&
#132800
0&
#133600
b10110 )
1&
#134400
0&
#135200
b10111 )
1&
#136000
0&
#136800
b11000 )
1&
#137600
0&
#138400
b11001 )
1&
#139200
0&
#140000
b11010 )
1&
#140800
0&
#141600
b11011 )
1&
#142400
0&
#143200
b11100 )
1&
#144000
0&
#144800
b11101 )
1&
#145600
0&
#146400
b11110 )
1&
#147200
0&
#148000
b11111 )
1&
#148800
0&
#149600
b100000 )
1&
#150400
0&
#151200
b100001 )
1&
#152000
0&
#152800
b100010 )
1&
#153600
0&
#154400
b100011 )
1&
#155200
0&
#156000
b100100 )
1&
#156800
0&
#157600
b100101 )
1&
#158400
0&
#159200
b100110 )
1&
#160000
0&
#160800
b100111 )
1&
#161600
0&
#162400
b101000 )
1&
#163200
0&
#164000
b101001 )
1&
#164800
0&
#165600
b101010 )
1&
#166400
0&
#167200
b101011 )
1&
#168000
0&
#168800
b101100 )
1&
#169600
0&
#170400
b101101 )
1&
#171200
0&
#172000
b101110 )
1&
#172800
0&
#173600
b101111 )
1&
#174400
0&
#175200
b110000 )
1&
#176000
0&
#176800
b110001 )
1&
#177600
0&
#178400
b110010 )
1&
#179200
0&
#180000
b110011 )
1&
#180800
0&
#181600
b110100 )
1&
#182400
0&
#183200
b110101 )
1&
#184000
0&
#184800
b110110 )
1&
#185600
0&
#186400
b110111 )
1&
#187200
0&
#188000
b111000 )
1&
#188800
0&
#189600
b111001 )
1&
#190400
0&
#191200
b111010 )
1&
#192000
0&
#192800
b111011 )
1&
#193600
0&
#194400
b111100 )
1&
#195200
0&
#196000
b111101 )
1&
#196800
0&
#197600
b111110 )
1&
#198400
0&
#199200
b111111 )
1&
#200000
0&
#200800
b0 )
1&
#201600
0&
#202400
11
b1 <
1(
1'
b1 )
1&
#203200
0&
#204000
b101001001001001010100110100100101001110010001110101111101000101010001000100011101000101 ,
01
1=
b1 "
b1 .
b1 :
0'
b10 )
1&
#204800
0&
#205600
b11 )
b11111111111 9
b1 #
b1 -
b1 ;
1&
#206400
0&
#207200
b11111111111 !
b11111111111 >
b111111111110 9
b10 #
b10 -
b10 ;
b100 )
1&
#208000
0&
#208800
b101 )
b111111111110 !
b111111111110 >
b1011111111101 9
b11 #
b11 -
b11 ;
1&
#209600
0&
#210400
b1011111111101 !
b1011111111101 >
b1111111111100 9
b100 #
b100 -
b100 ;
b110 )
1&
#211200
0&
#212000
b111 )
b1111111111100 !
b1111111111100 >
b10011111111011 9
b101 #
b101 -
b101 ;
1&
#212800
0&
#213600
b10011111111011 !
b10011111111011 >
b10111111111010 9
b110 #
b110 -
b110 ;
b1000 )
1&
#214400
0&
#215200
b1001 )
b10111111111010 !
b10111111111010 >
b11011111111001 9
b111 #
b111 -
b111 ;
1&
#216000
0&
#216800
b11011111111001 !
b11011111111001 >
b11111111111000 9
b1000 #
b1000 -
b1000 ;
b1010 )
1&
#217600
0&
#218400
b1011 )
b11111111111000 !
b11111111111000 >
b100011111110111 9
b1001 #
b1001 -
b1001 ;
1&
#219200
0&
#220000
b100011111110111 !
b100011111110111 >
b100111111110110 9
b1010 #
b1010 -
b1010 ;
b1100 )
1&
#220800
0&
#221600
b1101 )
b100111111110110 !
b100111111110110 >
b101011111110101 9
b1011 #
b1011 -
b1011 ;
1&
#222400
0&
#223200
b101011111110101 !
b101011111110101 >
b101111111110100 9
b1100 #
b1100 -
b1100 ;
b1110 )
1&
#224000
0&
#224800
b1111 )
b101111111110100 !
b101111111110100 >
b110011111110011 9
b1101 #
b1101 -
b1101 ;
1&
#225600
0&
#226400
b110011111110011 !
b110011111110011 >
b110111111110010 9
b1110 #
b1110 -
b1110 ;
b10000 )
1&
#227200
0&
#228000
b10 <
b10001 )
b110111111110010 !
b110111111110010 >
b111011111110001 9
b1111 #
b1111 -
b1111 ;
1&
#228800
0&
#229600
b101001101010100010001010100000101000100010110010101111101001000010010010100011101001000 ,
b111011111110001 !
b111011111110001 >
b111111111111111 9
b10000 #
b10000 -
b10000 ;
b10 "
b10 .
b10 :
b10010 )
1&
#230400
0&
#231200
b10011 )
b111111111111111 !
b111111111111111 >
b0 #
b0 -
b0 ;
1&
#232000
0&
#232800
b10100 )
1&
#233600
0&
#234400
b10101 )
1&
#235200
0&
#236000
b10110 )
1&
#236800
0&
#237600
b10111 )
1&
#238400
0&
#239200
b11000 )
1&
#240000
0&
#240800
b11001 )
1&
#241600
0&
#242400
b11010 )
1&
#243200
0&
#244000
b11011 )
1&
#244800
0&
#245600
b11100 )
1&
#246400
0&
#247200
b11101 )
1&
#248000
0&
#248800
b11110 )
1&
#249600
0&
#250400
b11111 )
1&
#251200
0&
#252000
b100000 )
1&
#252800
0&
#253600
b100001 )
1&
#254400
0&
#255200
b100010 )
1&
#256000
0&
#256800
b100011 )
1&
#257600
0&
#258400
b100100 )
1&
#259200
0&
#260000
b100101 )
1&
#260800
0&
#261600
b100110 )
1&
#262400
0&
#263200
b100111 )
1&
#264000
0&
#264800
b101000 )
1&
#265600
0&
#266400
b101001 )
1&
#267200
0&
#268000
b101010 )
1&
#268800
0&
#269600
b101011 )
1&
#270400
0&
#271200
b101100 )
1&
#272000
0&
#272800
b101101 )
1&
#273600
0&
#274400
b101110 )
1&
#275200
0&
#276000
b101111 )
1&
#276800
0&
#277600
b110000 )
1&
#278400
0&
#279200
b110001 )
1&
#280000
0&
#280800
b110010 )
1&
#281600
0&
#282400
b110011 )
1&
#283200
0&
#284000
b110100 )
1&
#284800
0&
#285600
b110101 )
1&
#286400
0&
#287200
b110110 )
1&
#288000
0&
#288800
b110111 )
1&
#289600
0&
#290400
b111000 )
1&
#291200
0&
#292000
b111001 )
1&
#292800
0&
#293600
b111010 )
1&
#294400
0&
#295200
b111011 )
1&
#296000
0&
#296800
b111100 )
1&
#297600
0&
#298400
b111101 )
1&
#299200
0&
#300000
b111110 )
1&
#300800
0&
#301600
b111111 )
1&
#302400
0&
#303200
b0 )
1&
#304000
0&
#304800
1'
b1 )
1&
#305600
0&
#306400
0'
b10 )
1&
#307200
0&
#308000
b11 )
1&
#308800
0&
#309600
b100 )
1&
#310400
0&
#311200
b101 )
1&
#312000
0&
#312800
b110 )
1&
#313600
0&
#314400
b111 )
1&
#315200
0&
#316000
b1000 )
1&
#316800
0&
#317600
b1001 )
1&
#318400
0&
#319200
b1010 )
1&
#320000
0&
#320800
b1011 )
1&
#321600
0&
#322400
b1100 )
1&
#323200
0&
#324000
b1101 )
1&
#324800
0&
#325600
b1110 )
1&
#326400
0&
#327200
b1111 )
1&
#328000
0&
#328800
b10000 )
1&
#329600
0&
#330400
b10001 )
1&
#331200
0&
#332000
b10010 )
1&
#332800
0&
#333600
b10011 )
1&
#334400
0&
#335200
b10100 )
1&
#336000
0&
#336800
b10101 )
1&
#337600
0&
#338400
b10110 )
1&
#339200
0&
#340000
b10111 )
1&
#340800
0&
#341600
b11000 )
1&
#342400
0&
#343200
b11001 )
1&
#344000
0&
#344800
b11010 )
1&
#345600
0&
#346400
b11011 )
1&
#347200
0&
#348000
b11100 )
1&
#348800
0&
#349600
b11101 )
1&
#350400
0&
#351200
b11110 )
1&
#352000
0&
#352800
b11111 )
1&
#353600
0&
#354400
b100000 )
1&
#355200
0&
#356000
b100001 )
1&
#356800
0&
#357600
b100010 )
1&
#358400
0&
#359200
b100011 )
1&
#360000
0&
#360800
b100100 )
1&
#361600
0&
#362400
b100101 )
1&
#363200
0&
#364000
b100110 )
1&
#364800
0&
#365600
b100111 )
1&
#366400
0&
#367200
b101000 )
1&
#368000
0&
#368800
b101001 )
1&
#369600
0&
#370400
b101010 )
1&
#371200
0&
#372000
b101011 )
1&
#372800
0&
#373600
b101100 )
1&
#374400
0&
#375200
b101101 )
1&
#376000
0&
#376800
b101110 )
1&
#377600
0&
#378400
b101111 )
1&
#379200
0&
#380000
b110000 )
1&
#380800
0&
#381600
b110001 )
1&
#382400
0&
#383200
b110010 )
1&
#384000
0&
#384800
b110011 )
1&
#385600
0&
#386400
b110100 )
1&
#387200
0&
#388000
b110101 )
1&
#388800
0&
#389600
b110110 )
1&
#390400
0&
#391200
b110111 )
1&
#392000
0&
#392800
b111000 )
1&
#393600
0&
#394400
b111001 )
1&
#395200
0&
#396000
b111010 )
1&
#396800
0&
#397600
b111011 )
1&
#398400
0&
#399200
b111100 )
1&
#400000
0&
#400800
b111101 )
1&
#401600
0&
#402400
b111110 )
1&
#403200
0&
#404000
b111111 )
1&
#404800
0&
#405600
b0 )
1&
#406400
0&
#407200
1'
b1 )
1&
#408000
0&
#408800
0'
b10 )
1&
#409600
0&
#410400
b11 )
1&
#411200
0&
#412000
b100 )
1&
#412800
0&
#413600
b101 )
1&
#414400
0&
#415200
b110 )
1&
#416000
0&
#416800
b111 )
1&
#417600
0&
#418400
b1000 )
1&
#419200
0&
#420000
b1001 )
1&
#420800
0&
#421600
b1010 )
1&
#422400
0&
#423200
b1011 )
1&
#424000
0&
#424800
b1100 )
1&
#425600
0&
#426400
b1101 )
1&
#427200
0&
#428000
b1110 )
1&
#428800
0&
#429600
b1111 )
1&
#430400
0&
#431200
b10000 )
1&
#432000
0&
#432800
b10001 )
1&
#433600
0&
#434400
b10010 )
1&
#435200
0&
#436000
b10011 )
1&
#436800
0&
#437600
b10100 )
1&
#438400
0&
#439200
b10101 )
1&
#440000
0&
#440800
b10110 )
1&
#441600
0&
#442400
b10111 )
1&
#443200
0&
#444000
b11000 )
1&
#444800
0&
#445600
b11001 )
1&
#446400
0&
#447200
b11010 )
1&
#448000
0&
#448800
b11011 )
1&
#449600
0&
#450400
b11100 )
1&
#451200
0&
#452000
b11101 )
1&
#452800
0&
#453600
b11110 )
1&
#454400
0&
#455200
b11111 )
1&
#456000
0&
#456800
b100000 )
1&
#457600
0&
#458400
b100001 )
1&
#459200
0&
#460000
b100010 )
1&
#460800
0&
#461600
b100011 )
1&
#462400
0&
#463200
b100100 )
1&
#464000
0&
#464800
b100101 )
1&
#465600
0&
#466400
b100110 )
1&
#467200
0&
#468000
b100111 )
1&
#468800
0&
#469600
b101000 )
1&
#470400
0&
#471200
b101001 )
1&
#472000
0&
#472800
b101010 )
1&
#473600
0&
#474400
b101011 )
1&
#475200
0&
#476000
b101100 )
1&
#476800
0&
#477600
b101101 )
1&
#478400
0&
#479200
b101110 )
1&
#480000
0&
#480800
b101111 )
1&
#481600
0&
#482400
b110000 )
1&
#483200
0&
#484000
b110001 )
1&
#484800
0&
#485600
b110010 )
1&
#486400
0&
#487200
b110011 )
1&
#488000
0&
#488800
b110100 )
1&
#489600
0&
#490400
b110101 )
1&
#491200
0&
#492000
b110110 )
1&
#492800
0&
#493600
b110111 )
1&
#494400
0&
#495200
b111000 )
1&
#496000
0&
#496800
b111001 )
1&
#497600
0&
#498400
b111010 )
1&
#499200
0&
#500000
b111011 )
1&
#500800
0&
#501600
b111100 )
1&
#502400
0&
#503200
b111101 )
1&
#504000
0&
#504800
b111110 )
1&
#505600
0&
#506400
b111111 )
1&
#507200
0&
#508000
b0 )
1&
#508800
0&
#509600
1'
b1 )
1&
#510400
0&
#511200
0'
b10 )
1&
#512000
0&
#512800
b11 )
1&
#513600
0&
#514400
b100 )
1&
#515200
0&
#516000
b101 )
1&
#516800
0&
#517600
b110 )
1&
#518400
0&
#519200
b111 )
1&
#520000
0&
#520800
b1000 )
1&
#521600
0&
#522400
b1001 )
1&
#523200
0&
#524000
b1010 )
1&
#524800
0&
#525600
b1011 )
1&
#526400
0&
#527200
b1100 )
1&
#528000
0&
#528800
b1101 )
1&
#529600
0&
#530400
b1110 )
1&
#531200
0&
#532000
b1111 )
1&
#532800
0&
#533600
b10000 )
1&
#534400
0&
#535200
b10001 )
1&
#536000
0&
#536800
b10010 )
1&
#537600
0&
#538400
b10011 )
1&
#539200
0&
#540000
b10100 )
1&
#540800
0&
#541600
b10101 )
1&
#542400
0&
#543200
b10110 )
1&
#544000
0&
#544800
b10111 )
1&
#545600
0&
#546400
b11000 )
1&
#547200
0&
#548000
b11001 )
1&
#548800
0&
#549600
b11010 )
1&
#550400
0&
#551200
b11011 )
1&
#552000
0&
#552800
b11100 )
1&
#553600
0&
#554400
b11101 )
1&
#555200
0&
#556000
b11110 )
1&
#556800
0&
#557600
b11111 )
1&
#558400
0&
#559200
b100000 )
1&
#560000
0&
#560800
b100001 )
1&
#561600
0&
#562400
b100010 )
1&
#563200
0&
#564000
b100011 )
1&
#564800
0&
#565600
b100100 )
1&
#566400
0&
#567200
b100101 )
1&
#568000
0&
#568800
b100110 )
1&
#569600
0&
#570400
b100111 )
1&
#571200
0&
#572000
b101000 )
1&
#572800
0&
#573600
b101001 )
1&
#574400
0&
#575200
b101010 )
1&
#576000
0&
#576800
b101011 )
1&
#577600
0&
#578400
b101100 )
1&
#579200
0&
#580000
b101101 )
1&
#580800
0&
#581600
b101110 )
1&
#582400
0&
#583200
b101111 )
1&
#584000
0&
#584800
b110000 )
1&
#585600
0&
#586400
b110001 )
1&
#587200
0&
#588000
b110010 )
1&
#588800
0&
#589600
b110011 )
1&
#590400
0&
#591200
b110100 )
1&
#592000
0&
#592800
b110101 )
1&
#593600
0&
#594400
b110110 )
1&
#595200
0&
#596000
b110111 )
1&
#596800
0&
#597600
b111000 )
1&
#598400
0&
#599200
b111001 )
1&
#600000
0&
#600800
b111010 )
1&
#601600
0&
#602400
b111011 )
1&
#603200
0&
#604000
b111100 )
1&
#604800
0&
#605600
b111101 )
1&
#606400
0&
#607200
b111110 )
1&
#608000
0&
#608800
b111111 )
1&
#609600
0&
#610400
b0 )
1&
#611200
0&
#612000
1'
b1 )
1&
#612800
0&
#613600
0'
b10 )
1&
#614400
0&
#615200
b11 )
1&
#616000
0&
#616800
b100 )
1&
#617600
0&
#618400
b101 )
1&
#619200
0&
#620000
b110 )
1&
#620800
0&
#621600
b111 )
1&
#622400
0&
#623200
b1000 )
1&
#624000
0&
#624800
b1001 )
1&
#625600
0&
#626400
b1010 )
1&
#627200
0&
#628000
b1011 )
1&
#628800
0&
#629600
b1100 )
1&
#630400
0&
#631200
b1101 )
1&
#632000
0&
#632800
b1110 )
1&
#633600
0&
#634400
b1111 )
1&
#635200
0&
#636000
b10000 )
1&
#636800
0&
#637600
b10001 )
1&
#638400
0&
#639200
b10010 )
1&
#640000
0&
#640800
b10011 )
1&
#641600
0&
#642400
b10100 )
1&
#643200
0&
#644000
b10101 )
1&
#644800
0&
#645600
b10110 )
1&
#646400
0&
#647200
b10111 )
1&
#648000
0&
#648800
b11000 )
1&
#649600
0&
#650400
b11001 )
1&
#651200
0&
#652000
b11010 )
1&
#652800
0&
#653600
b11011 )
1&
#654400
0&
#655200
b11100 )
1&
#656000
0&
#656800
b11101 )
1&
#657600
0&
#658400
b11110 )
1&
#659200
0&
#660000
b11111 )
1&
#660800
0&
#661600
b100000 )
1&
#662400
0&
#663200
b100001 )
1&
#664000
0&
#664800
b100010 )
1&
#665600
0&
#666400
b100011 )
1&
#667200
0&
#668000
b100100 )
1&
#668800
0&
#669600
b100101 )
1&
#670400
0&
#671200
b100110 )
1&
#672000
0&
#672800
b100111 )
1&
#673600
0&
#674400
b101000 )
1&
#675200
0&
#676000
b101001 )
1&
#676800
0&
#677600
b101010 )
1&
#678400
0&
#679200
b101011 )
1&
#680000
0&
#680800
b101100 )
1&
#681600
0&
#682400
b101101 )
1&
#683200
0&
#684000
b101110 )
1&
#684800
0&
#685600
b101111 )
1&
#686400
0&
#687200
b110000 )
1&
#688000
0&
#688800
b110001 )
1&
#689600
0&
#690400
b110010 )
1&
