Mine/prbs_core_lfsr.v
`timescale 1ns / 1ps
//////////////////////////////////////////////////////////////////////////////////
// 模块名称: prbs_core_lfsr
// 功能描述: 通用PRBS序列生成器，支持多种PN序列
//////////////////////////////////////////////////////////////////////////////////

module prbs_core_lfsr (
    input wire          dac_clk,            // 系统时钟，例如 625MHz
    input wire          reset_n,            // 同步低有效复位
    input wire          lfsr_clk_enable,    // LFSR移位使能脉冲 (来自 prbs_bitrate_clk_gen)
    input wire [4:0]    prbs_pn_select_reg, // PN阶数选择 (0:PN3, 1:PN5, 2:PN7, 3:PN9, 4:PN11, 5:PN15, 6:PN17, 7:PN23, 8:PN31, 9:PN13, 10:PN19, 11:PN21, 12:PN25, 13:PN27, 14:PN29)
    
    output reg          prbs_bit_out,       // 1位原始PRBS序列输出
    output reg          data_valid,         // 数据有效标志（每个完整序列周期置高一个时钟周期）
    output [MAX_PN_ORDER-1:0] lfsr_state     // 输出当前LFSR寄存器状态，用于调试
);

// 最大PN阶数，决定LFSR寄存器的最大位宽
localparam MAX_PN_ORDER = 33;

// 内部寄存器
reg [MAX_PN_ORDER-1:0] lfsr_reg;      // 存储LFSR状态
reg [31:0] bit_counter;               // 位计数器，用于生成data_valid信号
reg [31:0] sequence_length;           // 当前选择的序列长度

// 将当前LFSR状态输出到lfsr_state端口
assign lfsr_state = lfsr_reg;

// 抽头位置定义 (根据标准PN多项式)
reg [MAX_PN_ORDER-1:0] feedback_mask; // 用于选择抽头
wire                   feedback_bit;  // 反馈位

// 计算反馈位 - 对选中的抽头位进行异或
// 注意：我们使用标准的左移反馈移位寄存器(LFSR)实现
// 反馈位计算取决于多项式的具体形式
assign feedback_bit = ^(lfsr_reg & feedback_mask);

// 初始化
initial begin
    lfsr_reg = {{(MAX_PN_ORDER-1){1'b0}}, 1'b1}; // 默认种子，不能为全0
    prbs_bit_out = 1'b0;
    data_valid = 1'b0;
    bit_counter = 32'd0;
    sequence_length = 32'd0;
end

// 主要LFSR逻辑
always @(posedge dac_clk or negedge reset_n) begin
    if (!reset_n) begin
        lfsr_reg <= {{(MAX_PN_ORDER-1){1'b0}}, 1'b1}; // 复位为默认种子
        prbs_bit_out <= 1'b0;
        data_valid <= 1'b0;
        bit_counter <= 32'd0;
    end else if (lfsr_clk_enable) begin
        // 移位并插入反馈位
        case (prbs_pn_select_reg)
            5'd0: begin // PN3: x^3 + x + 1
                lfsr_reg <= {{(MAX_PN_ORDER-3){1'b0}}, feedback_bit, lfsr_reg[2:1]}; // 左移: 新的反馈位到D0，原D0到D1，原D1到D2
            end
            5'd1: begin // PN5: x^5 + x^2 + 1
                lfsr_reg <= {{(MAX_PN_ORDER-5){1'b0}}, feedback_bit, lfsr_reg[4:1]}; // 左移
            end
            5'd2: begin // PN7: x^7 + x^3 + 1
                lfsr_reg <= {{(MAX_PN_ORDER-7){1'b0}}, feedback_bit, lfsr_reg[6:1]}; // 左移
            end
            5'd3: begin // PN9: x^9 + x^4 + 1
                lfsr_reg <= {{(MAX_PN_ORDER-9){1'b0}}, feedback_bit, lfsr_reg[8:1]}; // 左移
            end
            5'd4: begin // PN11: x^11 + x^2 + 1
                lfsr_reg <= {{(MAX_PN_ORDER-11){1'b0}}, feedback_bit, lfsr_reg[10:1]}; // 左移
            end
            5'd5: begin // PN13: x^13 + x^4 + x^3 + x + 1
                lfsr_reg <= {{(MAX_PN_ORDER-13){1'b0}}, feedback_bit, lfsr_reg[12:1]}; // 左移
            end
            5'd6: begin // PN15: x^15 + x + 1
                lfsr_reg <= {{(MAX_PN_ORDER-15){1'b0}}, feedback_bit, lfsr_reg[14:1]}; // 左移
            end
            5'd7: begin // PN17: x^17 + x^3 + 1
                lfsr_reg <= {{(MAX_PN_ORDER-17){1'b0}}, feedback_bit, lfsr_reg[16:1]}; // 左移
            end
            5'd8: begin // PN19: x^19 + x^5 + x^2 + x + 1
                lfsr_reg <= {{(MAX_PN_ORDER-19){1'b0}}, feedback_bit, lfsr_reg[18:1]}; // 左移
            end
            5'd9: begin // PN21: x^21 + x^2 + 1
                lfsr_reg <= {{(MAX_PN_ORDER-21){1'b0}}, feedback_bit, lfsr_reg[20:1]}; // 左移
            end
            5'd10: begin // PN23: x^23 + x^5 + 1
                lfsr_reg <= {{(MAX_PN_ORDER-23){1'b0}}, feedback_bit, lfsr_reg[22:1]}; // 左移
            end
            5'd11: begin // PN25: x^25 + x^3 + 1
                lfsr_reg <= {{(MAX_PN_ORDER-25){1'b0}}, feedback_bit, lfsr_reg[24:1]}; // 左移
            end
            5'd12: begin // PN27: x^27 + x^5 + x^2 + x + 1
                lfsr_reg <= {{(MAX_PN_ORDER-27){1'b0}}, feedback_bit, lfsr_reg[26:1]}; // 左移
            end
            5'd13: begin // PN29: x^29 + x^2 + 1
                lfsr_reg <= {{(MAX_PN_ORDER-29){1'b0}}, feedback_bit, lfsr_reg[28:1]}; // 左移
            end
            5'd14: begin // PN31: x^31 + x^3 + 1
                lfsr_reg <= {{(MAX_PN_ORDER-31){1'b0}}, feedback_bit, lfsr_reg[30:1]}; // 左移
            end
            default: begin // 默认使用PN3
                lfsr_reg <= {{(MAX_PN_ORDER-3){1'b0}}, feedback_bit, lfsr_reg[2:1]}; // 左移
            end
        endcase
        
        // 输出LFSR的最高位作为PRBS输出
        prbs_bit_out <= lfsr_reg[0];
        
        // 位计数器逻辑，用于生成data_valid信号
        if (bit_counter >= sequence_length - 1) begin
            bit_counter <= 16'd0;
            data_valid <= 1'b1;
        end else begin
            bit_counter <= bit_counter + 16'd1;
            data_valid <= 1'b0;
        end
    end else begin
        data_valid <= 1'b0; // 当lfsr_clk_enable为低时，data_valid也为低
    end
end

// 根据 prbs_pn_select_reg 选择反馈多项式（抽头掩码）和序列长度
always @(*) begin
    case (prbs_pn_select_reg)
        5'd0: begin // PN3: x^3 + x + 1 (本原多项式)
            feedback_mask = {{(MAX_PN_ORDER-3){1'b0}}, 3'b101}; // 位2和位0反馈
            sequence_length = 32'd7; // 2^3 - 1 = 7
        end
        5'd1: begin // PN5: x^5 + x^2 + 1 (本原多项式)
            feedback_mask = {{(MAX_PN_ORDER-5){1'b0}}, 5'b01001}; // 位4和位1反馈
            sequence_length = 32'd31; // 2^5 - 1 = 31
        end
        5'd2: begin // PN7: x^7 + x^3 + 1 (本原多项式)
            feedback_mask = {{(MAX_PN_ORDER-7){1'b0}}, 7'b0010001}; // 位3和位0反馈
            sequence_length = 32'd127; // 2^7 - 1 = 127
        end
        5'd3: begin // PN9: x^9 + x^4 + 1 (本原多项式)
            feedback_mask = {{(MAX_PN_ORDER-9){1'b0}}, 9'b000100001}; // 位4和位0反馈
            sequence_length = 32'd511; // 2^9 - 1 = 511
        end
        5'd4: begin // PN11: x^11 + x^2 + 1 (本原多项式)
            feedback_mask = {{(MAX_PN_ORDER-11){1'b0}}, 11'b01000000001}; // 位2和位0反馈
            sequence_length = 32'd2047; // 2^11 - 1 = 2047
        end
        5'd5: begin // PN13: x^13 + x^4 + x^3 + x + 1 (本原多项式)
            feedback_mask = {{(MAX_PN_ORDER-13){1'b0}}, 13'b1011000000001}; // 位4、位3、位1和位0反馈
            sequence_length = 32'd8191; // 2^13 - 1 = 8191
        end
        5'd6: begin // PN15: x^15 + x + 1 (本原多项式)
            feedback_mask = {{(MAX_PN_ORDER-15){1'b0}}, 15'b100000000000001}; // 位1和位0反馈
            sequence_length = 32'd32767; // 2^15 - 1 = 32767
        end
        5'd7: begin // PN17: x^17 + x^3 + 1 (本原多项式)
            feedback_mask = {{(MAX_PN_ORDER-17){1'b0}}, 17'b00100000000000001}; // 位3和位0反馈
            sequence_length = 32'd131071; // 2^17 - 1 = 131071
        end
        5'd8: begin // PN19: x^19 + x^5 + x^2 + x + 1 (本原多项式)
            feedback_mask = {{(MAX_PN_ORDER-19){1'b0}}, 19'b1100100000000000001}; // 位5、位2、位1和位0反馈
            sequence_length = 32'd524287; // 2^19 - 1 = 524287
        end
        5'd9: begin // PN21: x^21 + x^2 + 1 (本原多项式)
            feedback_mask = {{(MAX_PN_ORDER-21){1'b0}}, 21'b010000000000000000001}; // 位2和位0反馈
            sequence_length = 32'd2097151; // 2^21 - 1 = 2097151
        end
        5'd10: begin // PN23: x^23 + x^5 + 1 (本原多项式)
            feedback_mask = {{(MAX_PN_ORDER-23){1'b0}}, 23'b00001000000000000000001}; // 位5和位0反馈
            sequence_length = 32'd8388607; // 2^23 - 1 = 8388607
        end
        5'd11: begin // PN25: x^25 + x^3 + 1 (本原多项式)
            feedback_mask = {{(MAX_PN_ORDER-25){1'b0}}, 25'b0010000000000000000000001}; // 位3和位0反馈
            sequence_length = 32'd33554431; // 2^25 - 1 = 33554431
        end
        5'd12: begin // PN27: x^27 + x^5 + x^2 + x + 1 (本原多项式)
            feedback_mask = {{(MAX_PN_ORDER-27){1'b0}}, 27'b100000000000000000000010011}; // 位5、位2、位1和位0反馈
            sequence_length = 32'd134217727; // 2^27 - 1 = 134217727
        end
        5'd13: begin // PN29: x^29 + x^2 + 1 (本原多项式)
            feedback_mask = {{(MAX_PN_ORDER-29){1'b0}}, 29'b10000000000000000000000000010}; // 位2和位0反馈
            sequence_length = 32'd536870911; // 2^29 - 1 = 536870911
        end
        5'd14: begin // PN31: x^31 + x^3 + 1 (本原多项式)
            feedback_mask = {{(MAX_PN_ORDER-31){1'b0}}, 31'b1000000000000000000000000000100}; // 位3和位0反馈
            sequence_length = 32'd2147483647; // 2^31 - 1 = 2147483647
        end
        default: begin // 默认使用PN3
            feedback_mask = {{(MAX_PN_ORDER-3){1'b0}}, 3'b011}; // 位1和位0反馈
            sequence_length = 32'd7; // 2^3 - 1 = 7
        end
    endcase
end

endmodule

Mine/prbs_bitrate_clk_gen.v
module prbs_bitrate_clk_gen (
    input wire          dac_clk,            // 主DAC时钟，例如 625MHz
    input wire          reset_n,            // 同步低有效复位
    input wire [31:0]   prbs_bit_rate_config_reg, // 32位NCO相位增量 (来自 CHANNEL_REG_CONFIG)

    output wire         lfsr_clk_enable     // 在每个PRBS比特周期开始时产生一个dac_clk周期的脉冲
);

// NCO 累加器位宽
localparam NCO_ACCUMULATOR_BITS = 32;

reg [NCO_ACCUMULATOR_BITS-1:0] phase_accumulator;
reg                             lfsr_clk_enable_reg;

// 用于检测相位溢出的信号
wire current_msb;
wire next_msb;
wire [NCO_ACCUMULATOR_BITS-1:0] next_phase;

// 使用assign语句进行赋值
assign next_phase = phase_accumulator + prbs_bit_rate_config_reg;
assign current_msb = phase_accumulator[NCO_ACCUMULATOR_BITS-1];
assign next_msb = next_phase[NCO_ACCUMULATOR_BITS-1];

// NCO 累加器
always @(posedge dac_clk or negedge reset_n) begin
    if (!reset_n) begin
        phase_accumulator   <= {NCO_ACCUMULATOR_BITS{1'b0}};
        lfsr_clk_enable_reg <= 1'b0;
    end else begin
        // 累加相位增量
        phase_accumulator <= phase_accumulator + prbs_bit_rate_config_reg;

        // 检测溢出（MSB跳变）产生使能脉冲
        // 当从0变成1时产生脉冲
        if (current_msb == 1'b0 && next_msb == 1'b1) begin
            lfsr_clk_enable_reg <= 1'b1; // 产生一个时钟周期的脉冲
        end else begin
            lfsr_clk_enable_reg <= 1'b0;
        end
    end
end

assign lfsr_clk_enable = lfsr_clk_enable_reg;

endmodule

Mine/prbs_generator_top.v
`timescale 1ns / 1ps
//////////////////////////////////////////////////////////////////////////////////
// 模块名称: prbs_generator_top
// 功能描述: PRBS生成器顶层模块，包含位率时钟生成和PRBS序列生成
//////////////////////////////////////////////////////////////////////////////////

module prbs_generator_top (
    input wire          dac_clk,                // 主DAC时钟，例如 625MHz
    input wire          reset_n,                // 同步低有效复位
    
    // 来自CHANNEL_REG_CONFIG的配置寄存器
    input wire          prbs_mode_select,       // 0: DDS, 1: PRBS
    input wire [4:0]    prbs_pn_select_reg,     // PN阶数选择 (0:PN3, 1:PN5, 2:PN7, 3:PN9, 4:PN11, 5:PN15, 6:PN17, 7:PN23, 8:PN31, 9:PN13, 10:PN19, 11:PN21, 12:PN25, 13:PN27, 14:PN29)
    input wire [31:0]   prbs_bit_rate_config_reg,// 位率NCO相位增量值
    input wire [7:0]    prbs_edge_time_config_reg,// 边沿过渡DAC周期数
    input wire [15:0]   prbs_amplitude_config_reg,// 幅度数字增益因子
    input wire [15:0]   prbs_dc_offset_config_reg,// 直流偏置数字值
    
    // 输出信号
    output wire         prbs_valid,             // PRBS数据有效标志
    output wire         prbs_bit_out_debug,     // 调试用：PRBS位输出
    output wire [15:0]  prbs_dac_data,          // 16位DAC数据输出
    output wire [32:0]  lfsr_state_debug        // 调试用：LFSR寄存器状态
);

// 内部连接信号
wire        lfsr_clk_enable;  // 位率时钟使能信号
wire        prbs_bit_out;     // 原始PRBS位输出
wire        data_valid;       // 数据有效标志
wire [32:0] lfsr_state;       // LFSR寄存器状态，用于调试

// 位率时钟生成模块实例化
prbs_bitrate_clk_gen bitrate_gen (
    .dac_clk(dac_clk),
    .reset_n(reset_n),
    .prbs_bit_rate_config_reg(prbs_bit_rate_config_reg),
    .lfsr_clk_enable(lfsr_clk_enable)
);

// PRBS序列生成器模块实例化
prbs_core_lfsr prbs_core (
    .dac_clk(dac_clk),
    .reset_n(reset_n),
    .lfsr_clk_enable(lfsr_clk_enable),
    .prbs_pn_select_reg(prbs_pn_select_reg),
    .prbs_bit_out(prbs_bit_out),
    .data_valid(data_valid),
    .lfsr_state(lfsr_state)
);

// 信号调制模块 - 将PRBS位转换为DAC数值
// prbs_modulator modulator (
//     .dac_clk(dac_clk),
//     .reset_n(reset_n),
//     .prbs_bit_in(prbs_bit_out),
//     .edge_time_config(prbs_edge_time_config_reg),
//     .amplitude_config(prbs_amplitude_config_reg),
//     .dc_offset_config(prbs_dc_offset_config_reg),
//     .dac_data_out(prbs_dac_data)
// );

// 输出赋值
assign prbs_valid = prbs_mode_select & data_valid;
assign prbs_bit_out_debug = prbs_bit_out;
assign lfsr_state_debug = lfsr_state;

// 由于暂时注释掉了prbs_modulator，我们直接将prbs_bit_out扩展为DAC数据
assign prbs_dac_data = prbs_bit_out ? 16'hFFFF : 16'h0000;

endmodule

Mine/prbs_generator_tb.v
`timescale 1ns / 1ps
//////////////////////////////////////////////////////////////////////////////////
// 模块名称: prbs_generator_tb
// 功能描述: PRBS生成器测试模块
//////////////////////////////////////////////////////////////////////////////////

module prbs_generator_tb();

// 时钟和复位信号
reg         dac_clk;
reg         reset_n;

// 配置寄存器
reg         prbs_mode_select;
reg [4:0]   prbs_pn_select_reg;
reg [31:0]  prbs_bit_rate_config_reg;
reg [7:0]   prbs_edge_time_config_reg;
reg [15:0]  prbs_amplitude_config_reg;
reg [15:0]  prbs_dc_offset_config_reg;

// 输出信号
wire        prbs_valid;
wire        prbs_bit_out_debug;
wire [15:0] prbs_dac_data;
wire [32:0] lfsr_state_debug;     // LFSR寄存器状态，用于调试

// 计数器和其他测试变量
integer     i;
integer     bit_count;
integer     sequence_count;

// 被测试模块实例化
prbs_generator_top uut (
    .dac_clk(dac_clk),
    .reset_n(reset_n),
    .prbs_mode_select(prbs_mode_select),
    .prbs_pn_select_reg(prbs_pn_select_reg),
    .prbs_bit_rate_config_reg(prbs_bit_rate_config_reg),
    .prbs_edge_time_config_reg(prbs_edge_time_config_reg),
    .prbs_amplitude_config_reg(prbs_amplitude_config_reg),
    .prbs_dc_offset_config_reg(prbs_dc_offset_config_reg),
    .prbs_valid(prbs_valid),
    .prbs_bit_out_debug(prbs_bit_out_debug),
    .prbs_dac_data(prbs_dac_data),
    .lfsr_state_debug(lfsr_state_debug)
);

// 时钟生成 - 625MHz的时钟周期为1.6ns
initial begin
    dac_clk = 0;
    forever #0.8 dac_clk = ~dac_clk; // 半周期0.8ns
end

// 注册波形文件
initial begin
    $dumpfile("prbs_sim.vcd");
    $dumpvars(0, prbs_generator_tb);
    $display("Starting simulation...");
end

// 测试过程
initial begin
    // 初始化
    reset_n = 0;
    prbs_mode_select = 1;  // 启用PRBS模式
    prbs_pn_select_reg = 0; // 选择PN5序列
    prbs_bit_rate_config_reg = 32'h10000000; // 位率设置 (约为625MHz/16)
    prbs_edge_time_config_reg = 8'd5; // 边沿过渡时间
    prbs_amplitude_config_reg = 16'h8000; // 满幅度
    prbs_dc_offset_config_reg = 16'h0000; // 无直流偏置
    bit_count = 0;
    sequence_count = 0;
    
    // 复位释放
    #100;
    reset_n = 1;
    
    // 运行一段时间观察PN3序列
    #10000;
    
    // 切换到PN7序列
    prbs_pn_select_reg = 1;
    #10000;
    
    // 调整位率
    prbs_bit_rate_config_reg = 32'h20000000; // 位率加倍
    #10000;
    
    // 切换到PN9序列
    prbs_pn_select_reg = 2;
    #10000;
    
    // 禁用PRBS模式
    prbs_mode_select = 0;
    #1000;
    
    // 重新启用PRBS模式
    prbs_mode_select = 1;
    #5000;
    
    // 结束仿真
    $finish;
end

// 监视PRBS位输出
always @(posedge dac_clk) begin
    if (reset_n && prbs_valid) begin
        $display("Time: %t, PRBS Bit: %b, DAC Data: %h", $time, prbs_bit_out_debug, prbs_dac_data);
        bit_count = bit_count + 1;
    end
end

// 监视序列完成信号
always @(posedge prbs_valid) begin
    if (reset_n) begin
        sequence_count = sequence_count + 1;
        $display("Time: %t, Sequence #%d completed", $time, sequence_count);
    end
end

endmodule

Mine/prbs_sim.vcd
$date
	Tue Jun  3 15:15:31 2025
$end
$version
	Icarus Verilog
$end
$timescale
	1ps
$end
$scope module prbs_generator_tb $end
$var wire 1 ! prbs_valid $end
$var wire 16 " prbs_dac_data [15:0] $end
$var wire 1 # prbs_bit_out_debug $end
$var wire 33 $ lfsr_state_debug [32:0] $end
$var reg 1 % dac_clk $end
$var reg 16 & prbs_amplitude_config_reg [15:0] $end
$var reg 32 ' prbs_bit_rate_config_reg [31:0] $end
$var reg 16 ( prbs_dc_offset_config_reg [15:0] $end
$var reg 8 ) prbs_edge_time_config_reg [7:0] $end
$var reg 1 * prbs_mode_select $end
$var reg 5 + prbs_pn_select_reg [4:0] $end
$var reg 1 , reset_n $end
$var integer 32 - bit_count [31:0] $end
$var integer 32 . sequence_count [31:0] $end
$scope module uut $end
$var wire 1 % dac_clk $end
$var wire 33 / lfsr_state_debug [32:0] $end
$var wire 16 0 prbs_amplitude_config_reg [15:0] $end
$var wire 1 # prbs_bit_out_debug $end
$var wire 32 1 prbs_bit_rate_config_reg [31:0] $end
$var wire 16 2 prbs_dc_offset_config_reg [15:0] $end
$var wire 8 3 prbs_edge_time_config_reg [7:0] $end
$var wire 1 * prbs_mode_select $end
$var wire 5 4 prbs_pn_select_reg [4:0] $end
$var wire 1 ! prbs_valid $end
$var wire 1 , reset_n $end
$var wire 16 5 prbs_dac_data [15:0] $end
$var wire 1 6 prbs_bit_out $end
$var wire 33 7 lfsr_state [32:0] $end
$var wire 1 8 lfsr_clk_enable $end
$var wire 1 9 data_valid $end
$scope module bitrate_gen $end
$var wire 1 % dac_clk $end
$var wire 1 8 lfsr_clk_enable $end
$var wire 32 : prbs_bit_rate_config_reg [31:0] $end
$var wire 1 , reset_n $end
$var wire 32 ; next_phase [31:0] $end
$var wire 1 < next_msb $end
$var wire 1 = current_msb $end
$var parameter 32 > NCO_ACCUMULATOR_BITS $end
$var reg 1 ? lfsr_clk_enable_reg $end
$var reg 32 @ phase_accumulator [31:0] $end
$upscope $end
$scope module prbs_core $end
$var wire 1 % dac_clk $end
$var wire 1 8 lfsr_clk_enable $end
$var wire 33 A lfsr_state [32:0] $end
$var wire 5 B prbs_pn_select_reg [4:0] $end
$var wire 1 , reset_n $end
$var wire 1 C feedback_bit $end
$var parameter 32 D MAX_PN_ORDER $end
$var reg 32 E bit_counter [31:0] $end
$var reg 1 9 data_valid $end
$var reg 33 F feedback_mask [32:0] $end
$var reg 33 G lfsr_reg [32:0] $end
$var reg 1 6 prbs_bit_out $end
$var reg 32 H sequence_length [31:0] $end
$upscope $end
$upscope $end
$upscope $end
$enddefinitions $end
$comment Show the parameter values. $end
$dumpall
b100001 D
b100000 >
$end
#0
$dumpvars
b111 H
b1 G
b101 F
b0 E
1C
b0 B
b1 A
b0 @
0?
0=
0<
b10000000000000000000000000000 ;
b10000000000000000000000000000 :
09
08
b1 7
06
b0 5
b0 4
b101 3
b0 2
b10000000000000000000000000000 1
b1000000000000000 0
b1 /
b0 .
b0 -
0,
b0 +
1*
b101 )
b0 (
b10000000000000000000000000000 '
b1000000000000000 &
0%
b1 $
0#
b0 "
0!
$end
#800
1%
#1600
0%
#2400
1%
#3200
0%
#4000
1%
#4800
0%
#5600
1%
#6400
0%
#7200
1%
#8000
0%
#8800
1%
#9600
0%
#10400
1%
#11200
0%
#12000
1%
#12800
0%
#13600
1%
#14400
0%
#15200
1%
#16000
0%
#16800
1%
#17600
0%
#18400
1%
#19200
0%
#20000
1%
#20800
0%
#21600
1%
#22400
0%
#23200
1%
#24000
0%
#24800
1%
#25600
0%
#26400
1%
#27200
0%
#28000
1%
#28800
0%
#29600
1%
#30400
0%
#31200
1%
#32000
0%
#32800
1%
#33600
0%
#34400
1%
#35200
0%
#36000
1%
#36800
0%
#37600
1%
#38400
0%
#39200
1%
#40000
0%
#40800
1%
#41600
0%
#42400
1%
#43200
0%
#44000
1%
#44800
0%
#45600
1%
#46400
0%
#47200
1%
#48000
0%
#48800
1%
#49600
0%
#50400
1%
#51200
0%
#52000
1%
#52800
0%
#53600
1%
#54400
0%
#55200
1%
#56000
0%
#56800
1%
#57600
0%
#58400
1%
#59200
0%
#60000
1%
#60800
0%
#61600
1%
#62400
0%
#63200
1%
#64000
0%
#64800
1%
#65600
0%
#66400
1%
#67200
0%
#68000
1%
#68800
0%
#69600
1%
#70400
0%
#71200
1%
#72000
0%
#72800
1%
#73600
0%
#74400
1%
#75200
0%
#76000
1%
#76800
0%
#77600
1%
#78400
0%
#79200
1%
#80000
0%
#80800
1%
#81600
0%
#82400
1%
#83200
0%
#84000
1%
#84800
0%
#85600
1%
#86400
0%
#87200
1%
#88000
0%
#88800
1%
#89600
0%
#90400
1%
#91200
0%
#92000
1%
#92800
0%
#93600
1%
#94400
0%
#95200
1%
#96000
0%
#96800
1%
#97600
0%
#98400
1%
#99200
0%
#100000
b100000000000000000000000000000 ;
b10000000000000000000000000000 @
1%
1,
#100800
0%
#101600
b110000000000000000000000000000 ;
b100000000000000000000000000000 @
1%
#102400
0%
#103200
b1000000000000000000000000000000 ;
b110000000000000000000000000000 @
1%
#104000
0%
#104800
b1010000000000000000000000000000 ;
b1000000000000000000000000000000 @
1%
#105600
0%
#106400
b1100000000000000000000000000000 ;
b1010000000000000000000000000000 @
1%
#107200
0%
#108000
b1110000000000000000000000000000 ;
b1100000000000000000000000000000 @
1%
#108800
0%
#109600
1<
b10000000000000000000000000000000 ;
b1110000000000000000000000000000 @
1%
#110400
0%
#111200
1=
18
1?
b10010000000000000000000000000000 ;
b10000000000000000000000000000000 @
1%
#112000
0%
#112800
b1111111111111111 "
b1111111111111111 5
b1 E
1#
16
b100 $
b100 /
b100 7
b100 A
b100 G
08
0?
b10100000000000000000000000000000 ;
b10010000000000000000000000000000 @
1%
#113600
0%
#114400
b10110000000000000000000000000000 ;
b10100000000000000000000000000000 @
1%
#115200
0%
#116000
b11000000000000000000000000000000 ;
b10110000000000000000000000000000 @
1%
#116800
0%
#117600
b11010000000000000000000000000000 ;
b11000000000000000000000000000000 @
1%
#118400
0%
#119200
b11100000000000000000000000000000 ;
b11010000000000000000000000000000 @
1%
#120000
0%
#120800
b11110000000000000000000000000000 ;
b11100000000000000000000000000000 @
1%
#121600
0%
#122400
0<
b0 ;
b11110000000000000000000000000000 @
1%
#123200
0%
#124000
0=
b10000000000000000000000000000 ;
b0 @
1%
#124800
0%
#125600
b100000000000000000000000000000 ;
b10000000000000000000000000000 @
1%
#126400
0%
#127200
b110000000000000000000000000000 ;
b100000000000000000000000000000 @
1%
#128000
0%
#128800
b1000000000000000000000000000000 ;
b110000000000000000000000000000 @
1%
#129600
0%
#130400
b1010000000000000000000000000000 ;
b1000000000000000000000000000000 @
1%
#131200
0%
#132000
b1100000000000000000000000000000 ;
b1010000000000000000000000000000 @
1%
#132800
0%
#133600
b1110000000000000000000000000000 ;
b1100000000000000000000000000000 @
1%
#134400
0%
#135200
1<
b10000000000000000000000000000000 ;
b1110000000000000000000000000000 @
1%
#136000
0%
#136800
1=
18
1?
b10010000000000000000000000000000 ;
b10000000000000000000000000000000 @
1%
#137600
0%
#138400
b0 "
b0 5
b10 E
0#
06
b110 $
b110 /
b110 7
b110 A
b110 G
08
0?
b10100000000000000000000000000000 ;
b10010000000000000000000000000000 @
1%
#139200
0%
#140000
b10110000000000000000000000000000 ;
b10100000000000000000000000000000 @
1%
#140800
0%
#141600
b11000000000000000000000000000000 ;
b10110000000000000000000000000000 @
1%
#142400
0%
#143200
b11010000000000000000000000000000 ;
b11000000000000000000000000000000 @
1%
#144000
0%
#144800
b11100000000000000000000000000000 ;
b11010000000000000000000000000000 @
1%
#145600
0%
#146400
b11110000000000000000000000000000 ;
b11100000000000000000000000000000 @
1%
#147200
0%
#148000
0<
b0 ;
b11110000000000000000000000000000 @
1%
#148800
0%
#149600
0=
b10000000000000000000000000000 ;
b0 @
1%
#150400
0%
#151200
b100000000000000000000000000000 ;
b10000000000000000000000000000 @
1%
#152000
0%
#152800
b110000000000000000000000000000 ;
b100000000000000000000000000000 @
1%
#153600
0%
#154400
b1000000000000000000000000000000 ;
b110000000000000000000000000000 @
1%
#155200
0%
#156000
b1010000000000000000000000000000 ;
b1000000000000000000000000000000 @
1%
#156800
0%
#157600
b1100000000000000000000000000000 ;
b1010000000000000000000000000000 @
1%
#158400
0%
#159200
b1110000000000000000000000000000 ;
b1100000000000000000000000000000 @
1%
#160000
0%
#160800
1<
b10000000000000000000000000000000 ;
b1110000000000000000000000000000 @
1%
#161600
0%
#162400
1=
18
1?
b10010000000000000000000000000000 ;
b10000000000000000000000000000000 @
1%
#163200
0%
#164000
0C
b11 E
b111 $
b111 /
b111 7
b111 A
b111 G
08
0?
b10100000000000000000000000000000 ;
b10010000000000000000000000000000 @
1%
#164800
0%
#165600
b10110000000000000000000000000000 ;
b10100000000000000000000000000000 @
1%
#166400
0%
#167200
b11000000000000000000000000000000 ;
b10110000000000000000000000000000 @
1%
#168000
0%
#168800
b11010000000000000000000000000000 ;
b11000000000000000000000000000000 @
1%
#169600
0%
#170400
b11100000000000000000000000000000 ;
b11010000000000000000000000000000 @
1%
#171200
0%
#172000
b11110000000000000000000000000000 ;
b11100000000000000000000000000000 @
1%
#172800
0%
#173600
0<
b0 ;
b11110000000000000000000000000000 @
1%
#174400
0%
#175200
0=
b10000000000000000000000000000 ;
b0 @
1%
#176000
0%
#176800
b100000000000000000000000000000 ;
b10000000000000000000000000000 @
1%
#177600
0%
#178400
b110000000000000000000000000000 ;
b100000000000000000000000000000 @
1%
#179200
0%
#180000
b1000000000000000000000000000000 ;
b110000000000000000000000000000 @
1%
#180800
0%
#181600
b1010000000000000000000000000000 ;
b1000000000000000000000000000000 @
1%
#182400
0%
#183200
b1100000000000000000000000000000 ;
b1010000000000000000000000000000 @
1%
#184000
0%
#184800
b1110000000000000000000000000000 ;
b1100000000000000000000000000000 @
1%
#185600
0%
#186400
1<
b10000000000000000000000000000000 ;
b1110000000000000000000000000000 @
1%
#187200
0%
#188000
1=
18
1?
b10010000000000000000000000000000 ;
b10000000000000000000000000000000 @
1%
#188800
0%
#189600
b1111111111111111 "
b1111111111111111 5
1C
b100 E
1#
16
b11 $
b11 /
b11 7
b11 A
b11 G
08
0?
b10100000000000000000000000000000 ;
b10010000000000000000000000000000 @
1%
#190400
0%
#191200
b10110000000000000000000000000000 ;
b10100000000000000000000000000000 @
1%
#192000
0%
#192800
b11000000000000000000000000000000 ;
b10110000000000000000000000000000 @
1%
#193600
0%
#194400
b11010000000000000000000000000000 ;
b11000000000000000000000000000000 @
1%
#195200
0%
#196000
b11100000000000000000000000000000 ;
b11010000000000000000000000000000 @
1%
#196800
0%
#197600
b11110000000000000000000000000000 ;
b11100000000000000000000000000000 @
1%
#198400
0%
#199200
0<
b0 ;
b11110000000000000000000000000000 @
1%
#200000
0%
#200800
0=
b10000000000000000000000000000 ;
b0 @
1%
#201600
0%
#202400
b100000000000000000000000000000 ;
b10000000000000000000000000000 @
1%
#203200
0%
#204000
b110000000000000000000000000000 ;
b100000000000000000000000000000 @
1%
#204800
0%
#205600
b1000000000000000000000000000000 ;
b110000000000000000000000000000 @
1%
#206400
0%
#207200
b1010000000000000000000000000000 ;
b1000000000000000000000000000000 @
1%
#208000
0%
#208800
b1100000000000000000000000000000 ;
b1010000000000000000000000000000 @
1%
#209600
0%
#210400
b1110000000000000000000000000000 ;
b1100000000000000000000000000000 @
1%
#211200
0%
#212000
1<
b10000000000000000000000000000000 ;
b1110000000000000000000000000000 @
1%
#212800
0%
#213600
1=
18
1?
b10010000000000000000000000000000 ;
b10000000000000000000000000000000 @
1%
#214400
0%
#215200
0C
b101 E
b101 $
b101 /
b101 7
b101 A
b101 G
08
0?
b10100000000000000000000000000000 ;
b10010000000000000000000000000000 @
1%
#216000
0%
#216800
b10110000000000000000000000000000 ;
b10100000000000000000000000000000 @
1%
#217600
0%
#218400
b11000000000000000000000000000000 ;
b10110000000000000000000000000000 @
1%
#219200
0%
#220000
b11010000000000000000000000000000 ;
b11000000000000000000000000000000 @
1%
#220800
0%
#221600
b11100000000000000000000000000000 ;
b11010000000000000000000000000000 @
1%
#222400
0%
#223200
b11110000000000000000000000000000 ;
b11100000000000000000000000000000 @
1%
#224000
0%
#224800
0<
b0 ;
b11110000000000000000000000000000 @
1%
#225600
0%
#226400
0=
b10000000000000000000000000000 ;
b0 @
1%
#227200
0%
