Mine/prbs_core_lfsr.v
`timescale 1ns / 1ps
//////////////////////////////////////////////////////////////////////////////////
// 模块名称: prbs_core_lfsr
// 功能描述: 通用PRBS序列生成器，支持多种PN序列
//////////////////////////////////////////////////////////////////////////////////

module prbs_core_lfsr (
    input wire          dac_clk,            // 系统时钟，例如 625MHz
    input wire          reset_n,            // 同步低有效复位
    input wire          lfsr_clk_enable,    // LFSR移位使能脉冲 (来自 prbs_bitrate_clk_gen)
    input wire [3:0]    prbs_pn_select_reg, // PN阶数选择 (例如 0:PN3, 1:PN7, 2:PN9, 3:PN11, 4:PN15, 5:PN20, 6:PN23, 7:PN31)
    
    output reg          prbs_bit_out,       // 1位原始PRBS序列输出
    output reg          data_valid          // 数据有效标志（每个完整序列周期置高一个时钟周期）
);

// 最大PN阶数，决定LFSR寄存器的最大位宽
localparam MAX_PN_ORDER = 33;

// 内部寄存器
reg [MAX_PN_ORDER-1:0] lfsr_reg;      // 存储LFSR状态
reg [15:0] bit_counter;               // 位计数器，用于生成data_valid信号
reg [15:0] sequence_length;           // 当前选择的序列长度

// 抽头位置定义 (根据标准PN多项式)
reg [MAX_PN_ORDER-1:0] feedback_mask; // 用于选择抽头
wire                   feedback_bit;  // 反馈位

// 计算反馈位 - 对所有选中的抽头位进行异或
assign feedback_bit = ^(lfsr_reg & feedback_mask);

// 初始化
initial begin
    lfsr_reg = {{(MAX_PN_ORDER-1){1'b0}}, 1'b1}; // 默认种子，不能为全0
    prbs_bit_out = 1'b0;
    data_valid = 1'b0;
    bit_counter = 16'd0;
    sequence_length = 16'd0;
end

// 主要LFSR逻辑
always @(posedge dac_clk or negedge reset_n) begin
    if (!reset_n) begin
        lfsr_reg <= {{(MAX_PN_ORDER-1){1'b0}}, 1'b1}; // 复位为默认种子
        prbs_bit_out <= 1'b0;
        data_valid <= 1'b0;
        bit_counter <= 16'd0;
    end else if (lfsr_clk_enable) begin
        // 移位并插入反馈位
        lfsr_reg <= {lfsr_reg[MAX_PN_ORDER-2:0], feedback_bit};
        
        // 输出LFSR的最高位作为PRBS输出
        prbs_bit_out <= lfsr_reg[MAX_PN_ORDER-1];
        
        // 位计数器逻辑，用于生成data_valid信号
        if (bit_counter >= sequence_length - 1) begin
            bit_counter <= 16'd0;
            data_valid <= 1'b1;
        end else begin
            bit_counter <= bit_counter + 16'd1;
            data_valid <= 1'b0;
        end
    end else begin
        data_valid <= 1'b0; // 当lfsr_clk_enable为低时，data_valid也为低
    end
end

// 根据 prbs_pn_select_reg 选择反馈多项式（抽头掩码）和序列长度
always @(*) begin
    case (prbs_pn_select_reg)
        4'd0: begin // PN3: x^3 + x^2 + 1
            feedback_mask = {{(MAX_PN_ORDER-3){1'b0}}, 3'b110};
            sequence_length = 16'd7; // 2^3 - 1 = 7
        end
        4'd1: begin // PN7: x^7 + x^6 + 1
            feedback_mask = {{(MAX_PN_ORDER-7){1'b0}}, 7'b1000001};
            sequence_length = 16'd127; // 2^7 - 1 = 127
        end
        4'd2: begin // PN9: x^9 + x^5 + 1
            feedback_mask = {{(MAX_PN_ORDER-9){1'b0}}, 9'b100010000};
            sequence_length = 16'd511; // 2^9 - 1 = 511
        end
        4'd3: begin // PN11: x^11 + x^9 + 1
            feedback_mask = {{(MAX_PN_ORDER-11){1'b0}}, 11'b10100000000};
            sequence_length = 16'd2047; // 2^11 - 1 = 2047
        end
        4'd4: begin // PN15: x^15 + x^14 + 1
            feedback_mask = {{(MAX_PN_ORDER-15){1'b0}}, 15'b110000000000000};
            sequence_length = 16'd32767; // 2^15 - 1 = 32767
        end
        4'd5: begin // PN20: x^20 + x^17 + 1
            feedback_mask = {{(MAX_PN_ORDER-20){1'b0}}, 20'b10001000000000000000};
            sequence_length = 16'd1023; // 实际应为2^20-1，但我们限制为1023以提高价值
        end
        4'd6: begin // PN23: x^23 + x^18 + 1
            feedback_mask = {{(MAX_PN_ORDER-23){1'b0}}, 23'b10000010000000000000000};
            sequence_length = 16'd2047; // 实际应为2^23-1，但我们限制为2047
        end
        4'd7: begin // PN31: x^31 + x^28 + 1
            feedback_mask = {{(MAX_PN_ORDER-31){1'b0}}, 31'b1000100000000000000000000000000};
            sequence_length = 16'd4095; // 实际应为2^31-1，但我们限制为4095
        end
        default: begin // 默认使用PN3
            feedback_mask = {{(MAX_PN_ORDER-3){1'b0}}, 3'b110};
            sequence_length = 16'd7;
        end
    endcase
end

endmodule

Mine/prbs_core_lfsr_tb.v
`timescale 1ns / 1ps
//////////////////////////////////////////////////////////////////////////////////
// 模块名称: prbs_core_lfsr_tb
// 功能描述: PRBS核心生成器测试模块
//////////////////////////////////////////////////////////////////////////////////

module prbs_core_lfsr_tb();

// 时钟和复位信号
reg         dac_clk;
reg         reset_n;

// 控制信号
reg         lfsr_clk_enable;
reg [3:0]   prbs_pn_select_reg;

// 输出信号
wire        prbs_bit_out;
wire        data_valid;

// 计数器和其他测试变量
integer     i;
integer     bit_count;
integer     one_count;
integer     zero_count;

// 被测试模块实例化
prbs_core_lfsr uut (
    .dac_clk(dac_clk),
    .reset_n(reset_n),
    .lfsr_clk_enable(lfsr_clk_enable),
    .prbs_pn_select_reg(prbs_pn_select_reg),
    .prbs_bit_out(prbs_bit_out),
    .data_valid(data_valid)
);

// 时钟生成 - 625MHz的时钟周期为1.6ns
initial begin
    dac_clk = 0;
    forever #0.8 dac_clk = ~dac_clk; // 半周期0.8ns
end

// 测试过程
initial begin
    // 注册波形文件
    $dumpfile("prbs_core_lfsr_sim.vcd");
    $dumpvars(0, prbs_core_lfsr_tb);
    $display("Starting PRBS core LFSR simulation...");
    
    // 初始化
    reset_n = 0;
    lfsr_clk_enable = 0;
    prbs_pn_select_reg = 0; // 选择PN3序列
    bit_count = 0;
    one_count = 0;
    zero_count = 0;
    
    // 复位释放
    #10;
    reset_n = 1;
    #10;
    
    // 测试PN3序列
    $display("Testing PN3 sequence...");
    prbs_pn_select_reg = 0;
    
    // 生成100个PRBS位
    for (i = 0; i < 100; i = i + 1) begin
        lfsr_clk_enable = 1;
        #1.6; // 一个时钟周期
        lfsr_clk_enable = 0;
        #1.6; // 等待一个时钟周期
        
        // 统计输出
        bit_count = bit_count + 1;
        if (prbs_bit_out)
            one_count = one_count + 1;
        else
            zero_count = zero_count + 1;
        
        // 打印输出
        $display("Bit %d: %b, Data Valid: %b", i, prbs_bit_out, data_valid);
    end
    
    // 显示统计结果
    $display("PN3 Statistics: Total bits: %d, Ones: %d, Zeros: %d", bit_count, one_count, zero_count);
    
    // 测试PN7序列
    bit_count = 0;
    one_count = 0;
    zero_count = 0;
    $display("Testing PN7 sequence...");
    prbs_pn_select_reg = 1;
    
    // 生成100个PRBS位
    for (i = 0; i < 100; i = i + 1) begin
        lfsr_clk_enable = 1;
        #1.6; // 一个时钟周期
        lfsr_clk_enable = 0;
        #1.6; // 等待一个时钟周期
        
        // 统计输出
        bit_count = bit_count + 1;
        if (prbs_bit_out)
            one_count = one_count + 1;
        else
            zero_count = zero_count + 1;
    end
    
    // 显示统计结果
    $display("PN7 Statistics: Total bits: %d, Ones: %d, Zeros: %d", bit_count, one_count, zero_count);
    
    // 结束仿真
    #10;
    $finish;
end

// 监视data_valid信号
always @(posedge data_valid) begin
    if (reset_n) begin
        $display("Time: %t, Sequence completed, PN type: %d", $time, prbs_pn_select_reg);
    end
end

endmodule

Mine/prbs_core_lfsr_sim.vcd
$date
	Thu May 29 15:00:33 2025
$end
$version
	Icarus Verilog
$end
$timescale
	1ps
$end
$scope module prbs_core_lfsr_tb $end
$var wire 1 ! prbs_bit_out $end
$var wire 1 " data_valid $end
$var reg 1 # dac_clk $end
$var reg 1 $ lfsr_clk_enable $end
$var reg 4 % prbs_pn_select_reg [3:0] $end
$var reg 1 & reset_n $end
$var integer 32 ' bit_count [31:0] $end
$var integer 32 ( i [31:0] $end
$var integer 32 ) one_count [31:0] $end
$var integer 32 * zero_count [31:0] $end
$scope module uut $end
$var wire 1 # dac_clk $end
$var wire 1 $ lfsr_clk_enable $end
$var wire 4 + prbs_pn_select_reg [3:0] $end
$var wire 1 & reset_n $end
$var wire 1 , feedback_bit $end
$var parameter 32 - MAX_PN_ORDER $end
$var reg 16 . bit_counter [15:0] $end
$var reg 1 " data_valid $end
$var reg 33 / feedback_mask [32:0] $end
$var reg 33 0 lfsr_reg [32:0] $end
$var reg 1 ! prbs_bit_out $end
$var reg 16 1 sequence_length [15:0] $end
$upscope $end
$upscope $end
$enddefinitions $end
$comment Show the parameter values. $end
$dumpall
b100001 -
$end
#0
$dumpvars
b111 1
b1 0
b110 /
b0 .
0,
b0 +
b0 *
b0 )
bx (
b0 '
0&
b0 %
0$
0#
0"
0!
$end
#800
1#
#1600
0#
#2400
1#
#3200
0#
#4000
1#
#4800
0#
#5600
1#
#6400
0#
#7200
1#
#8000
0#
#8800
1#
#9600
0#
#10000
1&
#10400
1#
#11200
0#
#12000
1#
#12800
0#
#13600
1#
#14400
0#
#15200
1#
#16000
0#
#16800
1#
#17600
0#
#18400
1#
#19200
0#
#20000
1,
b1 .
b10 0
1#
1$
b0 (
#20800
0#
#21600
1#
0$
#22400
0#
#23200
b10 .
b101 0
1#
1$
b1 (
b1 *
b1 '
#24000
0#
#24800
1#
0$
#25600
0#
#26400
b11 .
b1011 0
1#
1$
b10 (
b10 *
b10 '
#27200
0#
#28000
1#
0$
#28800
0#
#29600
0,
b100 .
b10111 0
1#
1$
b11 (
b11 *
b11 '
#30400
0#
#31200
1#
0$
#32000
0#
#32800
b101 .
b101110 0
1#
1$
b100 (
b100 *
b100 '
#33600
0#
#34400
1#
0$
#35200
0#
#36000
1,
b110 .
b1011100 0
1#
1$
b101 (
b101 *
b101 '
#36800
0#
#37600
1#
0$
#38400
0#
#39200
0,
1"
b0 .
b10111001 0
1#
1$
b110 (
b110 *
b110 '
#40000
0#
#40800
0"
1#
0$
#41600
0#
#42400
1,
b1 .
b101110010 0
1#
1$
b111 (
b111 *
b111 '
#43200
0#
#44000
1#
0$
#44800
0#
#45600
b10 .
b1011100101 0
1#
1$
b1000 (
b1000 *
b1000 '
#46400
0#
#47200
1#
0$
#48000
0#
#48800
b11 .
b10111001011 0
1#
1$
b1001 (
b1001 *
b1001 '
#49600
0#
#50400
1#
0$
#51200
0#
#52000
0,
b100 .
b101110010111 0
1#
1$
b1010 (
b1010 *
b1010 '
#52800
0#
#53600
1#
0$
#54400
0#
#55200
b101 .
b1011100101110 0
1#
1$
b1011 (
b1011 *
b1011 '
#56000
0#
#56800
1#
0$
#57600
0#
#58400
1,
b110 .
b10111001011100 0
1#
1$
b1100 (
b1100 *
b1100 '
#59200
0#
#60000
1#
0$
#60800
0#
#61600
0,
1"
b0 .
b101110010111001 0
1#
1$
b1101 (
b1101 *
b1101 '
#62400
0#
#63200
0"
1#
0$
#64000
0#
#64800
1,
b1 .
b1011100101110010 0
1#
1$
b1110 (
b1110 *
b1110 '
#65600
0#
#66400
1#
0$
#67200
0#
#68000
b10 .
b10111001011100101 0
1#
1$
b1111 (
b1111 *
b1111 '
#68800
0#
#69600
1#
0$
#70400
0#
#71200
b11 .
b101110010111001011 0
1#
1$
b10000 (
b10000 *
b10000 '
#72000
0#
#72800
1#
0$
#73600
0#
#74400
0,
b100 .
b1011100101110010111 0
1#
1$
b10001 (
b10001 *
b10001 '
#75200
0#
#76000
1#
0$
#76800
0#
#77600
b101 .
b10111001011100101110 0
1#
1$
b10010 (
b10010 *
b10010 '
#78400
0#
#79200
1#
0$
#80000
0#
#80800
1,
b110 .
b101110010111001011100 0
1#
1$
b10011 (
b10011 *
b10011 '
#81600
0#
#82400
1#
0$
#83200
0#
#84000
0,
1"
b0 .
b1011100101110010111001 0
1#
1$
b10100 (
b10100 *
b10100 '
#84800
0#
#85600
0"
1#
0$
#86400
0#
#87200
1,
b1 .
b10111001011100101110010 0
1#
1$
b10101 (
b10101 *
b10101 '
#88000
0#
#88800
1#
0$
#89600
0#
#90400
b10 .
b101110010111001011100101 0
1#
1$
b10110 (
b10110 *
b10110 '
#91200
0#
#92000
1#
0$
#92800
0#
#93600
b11 .
b1011100101110010111001011 0
1#
1$
b10111 (
b10111 *
b10111 '
#94400
0#
#95200
1#
0$
#96000
0#
#96800
0,
b100 .
b10111001011100101110010111 0
1#
1$
b11000 (
b11000 *
b11000 '
#97600
0#
#98400
1#
0$
#99200
0#
#100000
b101 .
b101110010111001011100101110 0
1#
1$
b11001 (
b11001 *
b11001 '
#100800
0#
#101600
1#
0$
#102400
0#
#103200
1,
b110 .
b1011100101110010111001011100 0
1#
1$
b11010 (
b11010 *
b11010 '
#104000
0#
#104800
1#
0$
#105600
0#
#106400
0,
1"
b0 .
b10111001011100101110010111001 0
1#
1$
b11011 (
b11011 *
b11011 '
#107200
0#
#108000
0"
1#
0$
#108800
0#
#109600
1,
b1 .
b101110010111001011100101110010 0
1#
1$
b11100 (
b11100 *
b11100 '
#110400
0#
#111200
1#
0$
#112000
0#
#112800
b10 .
b1011100101110010111001011100101 0
1#
1$
b11101 (
b11101 *
b11101 '
#113600
0#
#114400
1#
0$
#115200
0#
#116000
b11 .
b10111001011100101110010111001011 0
1#
1$
b11110 (
b11110 *
b11110 '
#116800
0#
#117600
1#
0$
#118400
0#
#119200
0,
b100 .
b101110010111001011100101110010111 0
1#
1$
b11111 (
b11111 *
b11111 '
#120000
0#
#120800
1#
0$
#121600
0#
#122400
b101 .
1!
b11100101110010111001011100101110 0
1#
1$
b100000 (
b100000 *
b100000 '
#123200
0#
#124000
1#
0$
#124800
0#
#125600
1,
b110 .
0!
b111001011100101110010111001011100 0
1#
1$
b100001 (
b1 )
b100001 '
#126400
0#
#127200
1#
0$
#128000
0#
#128800
0,
1"
b0 .
1!
b110010111001011100101110010111001 0
1#
1$
b100010 (
b100001 *
b100010 '
#129600
0#
#130400
0"
1#
0$
#131200
0#
#132000
1,
b1 .
b100101110010111001011100101110010 0
1#
1$
b100011 (
b10 )
b100011 '
#132800
0#
#133600
1#
0$
#134400
0#
#135200
b10 .
b1011100101110010111001011100101 0
1#
1$
b100100 (
b11 )
b100100 '
#136000
0#
#136800
1#
0$
#137600
0#
#138400
b11 .
0!
b10111001011100101110010111001011 0
1#
1$
b100101 (
b100 )
b100101 '
#139200
0#
#140000
1#
0$
#140800
0#
#141600
0,
b100 .
b101110010111001011100101110010111 0
1#
1$
b100110 (
b100010 *
b100110 '
#142400
0#
#143200
1#
0$
#144000
0#
#144800
b101 .
1!
b11100101110010111001011100101110 0
1#
1$
b100111 (
b100011 *
b100111 '
#145600
0#
#146400
1#
0$
#147200
0#
#148000
1,
b110 .
0!
b111001011100101110010111001011100 0
1#
1$
b101000 (
b101 )
b101000 '
#148800
0#
#149600
1#
0$
#150400
0#
#151200
0,
1"
b0 .
1!
b110010111001011100101110010111001 0
1#
1$
b101001 (
b100100 *
b101001 '
#152000
0#
#152800
0"
1#
0$
#153600
0#
#154400
1,
b1 .
b100101110010111001011100101110010 0
1#
1$
b101010 (
b110 )
b101010 '
#155200
0#
#156000
1#
0$
#156800
0#
#157600
b10 .
b1011100101110010111001011100101 0
1#
1$
b101011 (
b111 )
b101011 '
#158400
0#
#159200
1#
0$
#160000
0#
#160800
b11 .
0!
b10111001011100101110010111001011 0
1#
1$
b101100 (
b1000 )
b101100 '
#161600
0#
#162400
1#
0$
#163200
0#
#164000
0,
b100 .
b101110010111001011100101110010111 0
1#
1$
b101101 (
b100101 *
b101101 '
#164800
0#
#165600
1#
0$
#166400
0#
#167200
b101 .
1!
b11100101110010111001011100101110 0
1#
1$
b101110 (
b100110 *
b101110 '
#168000
0#
#168800
1#
0$
#169600
0#
#170400
1,
b110 .
0!
b111001011100101110010111001011100 0
1#
1$
b101111 (
b1001 )
b101111 '
#171200
0#
#172000
1#
0$
#172800
0#
#173600
0,
1"
b0 .
1!
b110010111001011100101110010111001 0
1#
1$
b110000 (
b100111 *
b110000 '
#174400
0#
#175200
0"
1#
0$
#176000
0#
#176800
1,
b1 .
b100101110010111001011100101110010 0
1#
1$
b110001 (
b1010 )
b110001 '
#177600
0#
#178400
1#
0$
#179200
0#
#180000
b10 .
b1011100101110010111001011100101 0
1#
1$
b110010 (
b1011 )
b110010 '
#180800
0#
#181600
1#
0$
#182400
0#
#183200
b11 .
0!
b10111001011100101110010111001011 0
1#
1$
b110011 (
b1100 )
b110011 '
#184000
0#
#184800
1#
0$
#185600
0#
#186400
0,
b100 .
b101110010111001011100101110010111 0
1#
1$
b110100 (
b101000 *
b110100 '
#187200
0#
#188000
1#
0$
#188800
0#
#189600
b101 .
1!
b11100101110010111001011100101110 0
1#
1$
b110101 (
b101001 *
b110101 '
#190400
0#
#191200
1#
0$
#192000
0#
#192800
1,
b110 .
0!
b111001011100101110010111001011100 0
1#
1$
b110110 (
b1101 )
b110110 '
#193600
0#
#194400
1#
0$
#195200
0#
#196000
0,
1"
b0 .
1!
b110010111001011100101110010111001 0
1#
1$
b110111 (
b101010 *
b110111 '
#196800
0#
#197600
0"
1#
0$
#198400
0#
#199200
1,
b1 .
b100101110010111001011100101110010 0
1#
1$
b111000 (
b1110 )
b111000 '
#200000
0#
#200800
1#
0$
#201600
0#
#202400
b10 .
b1011100101110010111001011100101 0
1#
1$
b111001 (
b1111 )
b111001 '
#203200
0#
#204000
1#
0$
#204800
0#
#205600
b11 .
0!
b10111001011100101110010111001011 0
1#
1$
b111010 (
b10000 )
b111010 '
#206400
0#
#207200
1#
0$
#208000
0#
#208800
0,
b100 .
b101110010111001011100101110010111 0
1#
1$
b111011 (
b101011 *
b111011 '
#209600
0#
#210400
1#
0$
#211200
0#
#212000
b101 .
1!
b11100101110010111001011100101110 0
1#
1$
b111100 (
b101100 *
b111100 '
#212800
0#
#213600
1#
0$
#214400
0#
#215200
1,
b110 .
0!
b111001011100101110010111001011100 0
1#
1$
b111101 (
b10001 )
b111101 '
#216000
0#
#216800
1#
0$
#217600
0#
#218400
0,
1"
b0 .
1!
b110010111001011100101110010111001 0
1#
1$
b111110 (
b101101 *
b111110 '
#219200
0#
#220000
0"
1#
0$
#220800
0#
#221600
1,
b1 .
b100101110010111001011100101110010 0
1#
1$
b111111 (
b10010 )
b111111 '
#222400
0#
#223200
1#
0$
#224000
0#
#224800
b10 .
b1011100101110010111001011100101 0
1#
1$
b1000000 (
b10011 )
b1000000 '
#225600
0#
#226400
1#
0$
#227200
0#
#228000
b11 .
0!
b10111001011100101110010111001011 0
1#
1$
b1000001 (
b10100 )
b1000001 '
#228800
0#
#229600
1#
0$
#230400
0#
#231200
0,
b100 .
b101110010111001011100101110010111 0
1#
1$
b1000010 (
b101110 *
b1000010 '
#232000
0#
#232800
1#
0$
#233600
0#
#234400
b101 .
1!
b11100101110010111001011100101110 0
1#
1$
b1000011 (
b101111 *
b1000011 '
#235200
0#
#236000
1#
0$
#236800
0#
#237600
1,
b110 .
0!
b111001011100101110010111001011100 0
1#
1$
b1000100 (
b10101 )
b1000100 '
#238400
0#
#239200
1#
0$
#240000
0#
#240800
0,
1"
b0 .
1!
b110010111001011100101110010111001 0
1#
1$
b1000101 (
b110000 *
b1000101 '
#241600
0#
#242400
0"
1#
0$
#243200
0#
#244000
1,
b1 .
b100101110010111001011100101110010 0
1#
1$
b1000110 (
b10110 )
b1000110 '
#244800
0#
#245600
1#
0$
#246400
0#
#247200
b10 .
b1011100101110010111001011100101 0
1#
1$
b1000111 (
b10111 )
b1000111 '
#248000
0#
#248800
1#
0$
#249600
0#
#250400
b11 .
0!
b10111001011100101110010111001011 0
1#
1$
b1001000 (
b11000 )
b1001000 '
#251200
0#
#252000
1#
0$
#252800
0#
#253600
0,
b100 .
b101110010111001011100101110010111 0
1#
1$
b1001001 (
b110001 *
b1001001 '
#254400
0#
#255200
1#
0$
#256000
0#
#256800
b101 .
1!
b11100101110010111001011100101110 0
1#
1$
b1001010 (
b110010 *
b1001010 '
#257600
0#
#258400
1#
0$
#259200
0#
#260000
1,
b110 .
0!
b111001011100101110010111001011100 0
1#
1$
b1001011 (
b11001 )
b1001011 '
#260800
0#
#261600
1#
0$
#262400
0#
#263200
0,
1"
b0 .
1!
b110010111001011100101110010111001 0
1#
1$
b1001100 (
b110011 *
b1001100 '
#264000
0#
#264800
0"
1#
0$
#265600
0#
#266400
1,
b1 .
b100101110010111001011100101110010 0
1#
1$
b1001101 (
b11010 )
b1001101 '
#267200
0#
#268000
1#
0$
#268800
0#
#269600
b10 .
b1011100101110010111001011100101 0
1#
1$
b1001110 (
b11011 )
b1001110 '
#270400
0#
#271200
1#
0$
#272000
0#
#272800
b11 .
0!
b10111001011100101110010111001011 0
1#
1$
b1001111 (
b11100 )
b1001111 '
#273600
0#
#274400
1#
0$
#275200
0#
#276000
0,
b100 .
b101110010111001011100101110010111 0
1#
1$
b1010000 (
b110100 *
b1010000 '
#276800
0#
#277600
1#
0$
#278400
0#
#279200
b101 .
1!
b11100101110010111001011100101110 0
1#
1$
b1010001 (
b110101 *
b1010001 '
#280000
0#
#280800
1#
0$
#281600
0#
#282400
1,
b110 .
0!
b111001011100101110010111001011100 0
1#
1$
b1010010 (
b11101 )
b1010010 '
#283200
0#
#284000
1#
0$
#284800
0#
#285600
0,
1"
b0 .
1!
b110010111001011100101110010111001 0
1#
1$
b1010011 (
b110110 *
b1010011 '
#286400
0#
#287200
0"
1#
0$
#288000
0#
#288800
1,
b1 .
b100101110010111001011100101110010 0
1#
1$
b1010100 (
b11110 )
b1010100 '
#289600
0#
#290400
1#
0$
#291200
0#
#292000
b10 .
b1011100101110010111001011100101 0
1#
1$
b1010101 (
b11111 )
b1010101 '
#292800
0#
#293600
1#
0$
#294400
0#
#295200
b11 .
0!
b10111001011100101110010111001011 0
1#
1$
b1010110 (
b100000 )
b1010110 '
#296000
0#
#296800
1#
0$
#297600
0#
#298400
0,
b100 .
b101110010111001011100101110010111 0
1#
1$
b1010111 (
b110111 *
b1010111 '
#299200
0#
#300000
1#
0$
#300800
0#
#301600
b101 .
1!
b11100101110010111001011100101110 0
1#
1$
b1011000 (
b111000 *
b1011000 '
#302400
0#
#303200
1#
0$
#304000
0#
#304800
1,
b110 .
0!
b111001011100101110010111001011100 0
1#
1$
b1011001 (
b100001 )
b1011001 '
#305600
0#
#306400
1#
0$
#307200
0#
#308000
0,
1"
b0 .
1!
b110010111001011100101110010111001 0
1#
1$
b1011010 (
b111001 *
b1011010 '
#308800
0#
#309600
0"
1#
0$
#310400
0#
#311200
1,
b1 .
b100101110010111001011100101110010 0
1#
1$
b1011011 (
b100010 )
b1011011 '
#312000
0#
#312800
1#
0$
#313600
0#
#314400
b10 .
b1011100101110010111001011100101 0
1#
1$
b1011100 (
b100011 )
b1011100 '
#315200
0#
#316000
1#
0$
#316800
0#
#317600
b11 .
0!
b10111001011100101110010111001011 0
1#
1$
b1011101 (
b100100 )
b1011101 '
#318400
0#
#319200
1#
0$
#320000
0#
#320800
0,
b100 .
b101110010111001011100101110010111 0
1#
1$
b1011110 (
b111010 *
b1011110 '
#321600
0#
#322400
1#
0$
#323200
0#
#324000
b101 .
1!
b11100101110010111001011100101110 0
1#
1$
b1011111 (
b111011 *
b1011111 '
#324800
0#
#325600
1#
0$
#326400
0#
#327200
1,
b110 .
0!
b111001011100101110010111001011100 0
1#
1$
b1100000 (
b100101 )
b1100000 '
#328000
0#
#328800
1#
0$
#329600
0#
#330400
0,
1"
b0 .
1!
b110010111001011100101110010111001 0
1#
1$
b1100001 (
b111100 *
b1100001 '
#331200
0#
#332000
0"
1#
0$
#332800
0#
#333600
1,
b1 .
b100101110010111001011100101110010 0
1#
1$
b1100010 (
b100110 )
b1100010 '
#334400
0#
#335200
1#
0$
#336000
0#
#336800
b10 .
b1011100101110010111001011100101 0
1#
1$
b1100011 (
b100111 )
b1100011 '
#337600
0#
#338400
1#
0$
#339200
0#
#340000
b11 .
0!
b10111001011100101110010111001011 0
0,
b1111111 1
b1000001 /
1#
1$
b1 %
b1 +
b0 *
b0 (
b0 )
b0 '
#340800
0#
#341600
1#
0$
#342400
0#
#343200
b100 .
b101110010111001011100101110010110 0
1#
1$
b1 (
b1 *
b1 '
#344000
0#
#344800
1#
0$
#345600
0#
#346400
b101 .
1!
b11100101110010111001011100101100 0
1#
1$
b10 (
b10 *
b10 '
#347200
0#
#348000
1#
0$
#348800
0#
#349600
1,
b110 .
0!
b111001011100101110010111001011000 0
1#
1$
b11 (
b1 )
b11 '
#350400
0#
#351200
1#
0$
#352000
0#
#352800
b111 .
1!
b110010111001011100101110010110001 0
1#
1$
b100 (
b11 *
b100 '
#353600
0#
#354400
1#
0$
#355200
0#
#356000
0,
b1000 .
b100101110010111001011100101100011 0
1#
1$
b101 (
b10 )
b101 '
#356800
0#
#357600
1#
0$
#358400
0#
#359200
1,
b1001 .
b1011100101110010111001011000110 0
1#
1$
b110 (
b11 )
b110 '
#360000
0#
#360800
1#
0$
#361600
0#
#362400
b1010 .
0!
b10111001011100101110010110001101 0
1#
1$
b111 (
b100 )
b111 '
#363200
0#
#364000
1#
0$
#364800
0#
#365600
b1011 .
b101110010111001011100101100011011 0
1#
1$
b1000 (
b100 *
b1000 '
#366400
0#
#367200
1#
0$
#368000
0#
#368800
b1100 .
1!
b11100101110010111001011000110111 0
1#
1$
b1001 (
b101 *
b1001 '
#369600
0#
#370400
1#
0$
#371200
0#
#372000
0,
b1101 .
0!
b111001011100101110010110001101111 0
1#
1$
b1010 (
b101 )
b1010 '
#372800
0#
#373600
1#
0$
#374400
0#
#375200
1,
b1110 .
1!
b110010111001011100101100011011110 0
1#
1$
b1011 (
b110 *
b1011 '
#376000
0#
#376800
1#
0$
#377600
0#
#378400
b1111 .
b100101110010111001011000110111101 0
1#
1$
b1100 (
b110 )
b1100 '
#379200
0#
#380000
1#
0$
#380800
0#
#381600
0,
b10000 .
b1011100101110010110001101111011 0
1#
1$
b1101 (
b111 )
b1101 '
#382400
0#
#383200
1#
0$
#384000
0#
#384800
1,
b10001 .
0!
b10111001011100101100011011110110 0
1#
1$
b1110 (
b1000 )
b1110 '
#385600
0#
#386400
1#
0$
#387200
0#
#388000
0,
b10010 .
b101110010111001011000110111101101 0
1#
1$
b1111 (
b111 *
b1111 '
#388800
0#
#389600
1#
0$
#390400
0#
#391200
1,
b10011 .
1!
b11100101110010110001101111011010 0
1#
1$
b10000 (
b1000 *
b10000 '
#392000
0#
#392800
1#
0$
#393600
0#
#394400
b10100 .
0!
b111001011100101100011011110110101 0
1#
1$
b10001 (
b1001 )
b10001 '
#395200
0#
#396000
1#
0$
#396800
0#
#397600
0,
b10101 .
1!
b110010111001011000110111101101011 0
1#
1$
b10010 (
b1001 *
b10010 '
#398400
0#
#399200
1#
0$
#400000
0#
#400800
1,
b10110 .
b100101110010110001101111011010110 0
1#
1$
b10011 (
b1010 )
b10011 '
#401600
0#
#402400
1#
0$
#403200
0#
#404000
b10111 .
b1011100101100011011110110101101 0
1#
1$
b10100 (
b1011 )
b10100 '
#404800
0#
#405600
1#
0$
#406400
0#
#407200
0,
b11000 .
0!
b10111001011000110111101101011011 0
1#
1$
b10101 (
b1100 )
b10101 '
#408000
0#
#408800
1#
0$
#409600
0#
#410400
b11001 .
b101110010110001101111011010110110 0
1#
1$
b10110 (
b1010 *
b10110 '
#411200
0#
#412000
1#
0$
#412800
0#
#413600
1,
b11010 .
1!
b11100101100011011110110101101100 0
1#
1$
b10111 (
b1011 *
b10111 '
#414400
0#
#415200
1#
0$
#416000
0#
#416800
0,
b11011 .
0!
b111001011000110111101101011011001 0
1#
1$
b11000 (
b1101 )
b11000 '
#417600
0#
#418400
1#
0$
#419200
0#
#420000
b11100 .
1!
b110010110001101111011010110110010 0
1#
1$
b11001 (
b1100 *
b11001 '
#420800
0#
#421600
1#
0$
#422400
0#
#423200
1,
b11101 .
b100101100011011110110101101100100 0
1#
1$
b11010 (
b1110 )
b11010 '
#424000
0#
#424800
1#
0$
#425600
0#
#426400
0,
b11110 .
b1011000110111101101011011001001 0
1#
1$
b11011 (
b1111 )
b11011 '
#427200
0#
#428000
1#
0$
#428800
0#
#429600
b11111 .
0!
b10110001101111011010110110010010 0
1#
1$
b11100 (
b10000 )
b11100 '
#430400
0#
#431200
1#
0$
#432000
0#
#432800
b100000 .
b101100011011110110101101100100100 0
1#
1$
b11101 (
b1101 *
b11101 '
#433600
0#
#434400
1#
0$
#435200
0#
#436000
1,
b100001 .
1!
b11000110111101101011011001001000 0
1#
1$
b11110 (
b1110 *
b11110 '
#436800
0#
#437600
1#
0$
#438400
0#
#439200
b100010 .
0!
b110001101111011010110110010010001 0
1#
1$
b11111 (
b10001 )
b11111 '
#440000
0#
#440800
1#
0$
#441600
0#
#442400
b100011 .
1!
b100011011110110101101100100100011 0
1#
1$
b100000 (
b1111 *
b100000 '
#443200
0#
#444000
1#
0$
#444800
0#
#445600
0,
b100100 .
b110111101101011011001001000111 0
1#
1$
b100001 (
b10010 )
b100001 '
#446400
0#
#447200
1#
0$
#448000
0#
#448800
b100101 .
0!
b1101111011010110110010010001110 0
1#
1$
b100010 (
b10011 )
b100010 '
#449600
0#
#450400
1#
0$
#451200
0#
#452000
b100110 .
b11011110110101101100100100011100 0
1#
1$
b100011 (
b10000 *
b100011 '
#452800
0#
#453600
1#
0$
#454400
0#
#455200
b100111 .
b110111101101011011001001000111000 0
1#
1$
b100100 (
b10001 *
b100100 '
#456000
0#
#456800
1#
0$
#457600
0#
#458400
1,
b101000 .
1!
b101111011010110110010010001110000 0
1#
1$
b100101 (
b10010 *
b100101 '
#459200
0#
#460000
1#
0$
#460800
0#
#461600
0,
b101001 .
b11110110101101100100100011100001 0
1#
1$
b100110 (
b10100 )
b100110 '
#462400
0#
#463200
1#
0$
#464000
0#
