Mine/prbs_core_lfsr.v
`timescale 1ns / 1ps
//////////////////////////////////////////////////////////////////////////////////
// 模块名称: prbs_core_lfsr
// 功能描述: 通用PRBS序列生成器，支持多种PN序列
//////////////////////////////////////////////////////////////////////////////////

module prbs_core_lfsr (
    input wire          dac_clk,            // 系统时钟，例如 625MHz
    input wire          reset_n,            // 同步低有效复位
    input wire          lfsr_clk_enable,    // LFSR移位使能脉冲 (来自 prbs_bitrate_clk_gen)
    input wire [4:0]    prbs_pn_select_reg, // PN阶数选择 (0:PN3, 1:PN5, 2:PN7, 3:PN9, 4:PN11, 5:PN15, 6:PN17, 7:PN23, 8:PN31, 9:PN13, 10:PN19, 11:PN21, 12:PN25, 13:PN27, 14:PN29)
    
    output reg          prbs_bit_out,       // 1位原始PRBS序列输出
    output reg          data_valid,         // 数据有效标志（每个完整序列周期置高一个时钟周期）
    output [MAX_PN_ORDER-1:0] lfsr_state     // 输出当前LFSR寄存器状态，用于调试
);

// 最大PN阶数，决定LFSR寄存器的最大位宽
localparam MAX_PN_ORDER = 33;

// 内部寄存器
reg [MAX_PN_ORDER-1:0] lfsr_reg;      // 存储LFSR状态
reg [31:0] bit_counter;               // 位计数器，用于生成data_valid信号
reg [31:0] sequence_length;           // 当前选择的序列长度

// 将当前LFSR状态输出到lfsr_state端口
assign lfsr_state = lfsr_reg;

// 抽头位置定义 (根据标准PN多项式)
reg [MAX_PN_ORDER-1:0] feedback_mask; // 用于选择抽头
wire                   feedback_bit;  // 反馈位

// 计算反馈位 - 对选中的抽头位进行异或
// 注意：我们使用标准的左移反馈移位寄存器(LFSR)实现
// 反馈位计算取决于多项式的具体形式
assign feedback_bit = ^(lfsr_reg & feedback_mask);

// 初始化
initial begin
    lfsr_reg = {{(MAX_PN_ORDER-1){1'b0}}, 1'b1}; // 默认种子，不能为全0
    prbs_bit_out = 1'b0;
    data_valid = 1'b0;
    bit_counter = 16'd0;
    sequence_length = 16'd0;
end

// 主要LFSR逻辑
always @(posedge dac_clk or negedge reset_n) begin
    if (!reset_n) begin
        lfsr_reg <= {{(MAX_PN_ORDER-1){1'b0}}, 1'b1}; // 复位为默认种子
        prbs_bit_out <= 1'b0;
        data_valid <= 1'b0;
        bit_counter <= 32'd0;
    end else if (lfsr_clk_enable) begin
        // 移位并插入反馈位
        case (prbs_pn_select_reg)
            5'd0: begin // PN3: x^3 + x + 1
                lfsr_reg <= {{(MAX_PN_ORDER-3){1'b0}}, feedback_bit, lfsr_reg[2:1]}; // 左移: 新的反馈位到D0，原D0到D1，原D1到D2
            end
            5'd1: begin // PN5: x^5 + x^2 + 1
                lfsr_reg <= {{(MAX_PN_ORDER-5){1'b0}}, feedback_bit, lfsr_reg[4:1]}; // 左移
            end
            5'd2: begin // PN7: x^7 + x^3 + 1
                lfsr_reg <= {{(MAX_PN_ORDER-7){1'b0}}, feedback_bit, lfsr_reg[6:1]}; // 左移
            end
            5'd3: begin // PN9: x^9 + x^4 + 1
                lfsr_reg <= {{(MAX_PN_ORDER-9){1'b0}}, feedback_bit, lfsr_reg[8:1]}; // 左移
            end
            5'd4: begin // PN11: x^11 + x^2 + 1
                lfsr_reg <= {{(MAX_PN_ORDER-11){1'b0}}, feedback_bit, lfsr_reg[10:1]}; // 左移
            end
            5'd5: begin // PN13: x^13 + x^4 + x^3 + x + 1
                lfsr_reg <= {{(MAX_PN_ORDER-13){1'b0}}, feedback_bit, lfsr_reg[12:1]}; // 左移
            end
            5'd6: begin // PN15: x^15 + x + 1
                lfsr_reg <= {{(MAX_PN_ORDER-15){1'b0}}, feedback_bit, lfsr_reg[14:1]}; // 左移
            end
            5'd7: begin // PN17: x^17 + x^3 + 1
                lfsr_reg <= {{(MAX_PN_ORDER-17){1'b0}}, feedback_bit, lfsr_reg[16:1]}; // 左移
            end
            5'd8: begin // PN19: x^19 + x^5 + x^2 + x + 1
                lfsr_reg <= {{(MAX_PN_ORDER-19){1'b0}}, feedback_bit, lfsr_reg[18:1]}; // 左移
            end
            5'd9: begin // PN21: x^21 + x^2 + 1
                lfsr_reg <= {{(MAX_PN_ORDER-21){1'b0}}, feedback_bit, lfsr_reg[20:1]}; // 左移
            end
            5'd10: begin // PN23: x^23 + x^5 + 1
                lfsr_reg <= {{(MAX_PN_ORDER-23){1'b0}}, feedback_bit, lfsr_reg[22:1]}; // 左移
            end
            5'd11: begin // PN25: x^25 + x^3 + 1
                lfsr_reg <= {{(MAX_PN_ORDER-25){1'b0}}, feedback_bit, lfsr_reg[24:1]}; // 左移
            end
            5'd12: begin // PN27: x^27 + x^5 + x^2 + x + 1
                lfsr_reg <= {{(MAX_PN_ORDER-27){1'b0}}, feedback_bit, lfsr_reg[26:1]}; // 左移
            end
            5'd13: begin // PN29: x^29 + x^2 + 1
                lfsr_reg <= {{(MAX_PN_ORDER-29){1'b0}}, feedback_bit, lfsr_reg[28:1]}; // 左移
            end
            5'd14: begin // PN31: x^31 + x^3 + 1
                lfsr_reg <= {{(MAX_PN_ORDER-31){1'b0}}, feedback_bit, lfsr_reg[30:1]}; // 左移
            end
            default: begin // 默认使用PN3
                lfsr_reg <= {{(MAX_PN_ORDER-3){1'b0}}, feedback_bit, lfsr_reg[2:1]}; // 左移
            end
        endcase
        
        // 输出LFSR的最高位作为PRBS输出
        prbs_bit_out <= lfsr_reg[MAX_PN_ORDER-1];
        
        // 位计数器逻辑，用于生成data_valid信号
        if (bit_counter >= sequence_length - 1) begin
            bit_counter <= 16'd0;
            data_valid <= 1'b1;
        end else begin
            bit_counter <= bit_counter + 16'd1;
            data_valid <= 1'b0;
        end
    end else begin
        data_valid <= 1'b0; // 当lfsr_clk_enable为低时，data_valid也为低
    end
end

// 根据 prbs_pn_select_reg 选择反馈多项式（抽头掩码）和序列长度
always @(*) begin
    case (prbs_pn_select_reg)
        5'd0: begin // PN3: x^3 + x + 1 (本原多项式)
            feedback_mask = {{(MAX_PN_ORDER-3){1'b0}}, 3'b101}; // 位2和位0反馈
            sequence_length = 32'd7; // 2^3 - 1 = 7
        end
        5'd1: begin // PN5: x^5 + x^2 + 1 (本原多项式)
            feedback_mask = {{(MAX_PN_ORDER-5){1'b0}}, 5'b01001}; // 位4和位1反馈
            sequence_length = 32'd31; // 2^5 - 1 = 31
        end
        5'd2: begin // PN7: x^7 + x^3 + 1 (本原多项式)
            feedback_mask = {{(MAX_PN_ORDER-7){1'b0}}, 7'b0010001}; // 位3和位0反馈
            sequence_length = 32'd127; // 2^7 - 1 = 127
        end
        5'd3: begin // PN9: x^9 + x^4 + 1 (本原多项式)
            feedback_mask = {{(MAX_PN_ORDER-9){1'b0}}, 9'b100001000}; // 位4和位0反馈
            sequence_length = 32'd511; // 2^9 - 1 = 511
        end
        5'd4: begin // PN11: x^11 + x^2 + 1 (本原多项式)
            feedback_mask = {{(MAX_PN_ORDER-11){1'b0}}, 11'b10000000010}; // 位2和位0反馈
            sequence_length = 32'd2047; // 2^11 - 1 = 2047
        end
        5'd5: begin // PN13: x^13 + x^4 + x^3 + x + 1 (本原多项式)
            feedback_mask = {{(MAX_PN_ORDER-13){1'b0}}, 13'b1000000001101}; // 位4、位3、位1和位0反馈
            sequence_length = 32'd8191; // 2^13 - 1 = 8191
        end
        5'd6: begin // PN15: x^15 + x + 1 (本原多项式)
            feedback_mask = {{(MAX_PN_ORDER-15){1'b0}}, 15'b100000000000001}; // 位1和位0反馈
            sequence_length = 32'd32767; // 2^15 - 1 = 32767
        end
        5'd7: begin // PN17: x^17 + x^3 + 1 (本原多项式)
            feedback_mask = {{(MAX_PN_ORDER-17){1'b0}}, 17'b10000000000000100}; // 位3和位0反馈
            sequence_length = 32'd131071; // 2^17 - 1 = 131071
        end
        5'd8: begin // PN19: x^19 + x^5 + x^2 + x + 1 (本原多项式)
            feedback_mask = {{(MAX_PN_ORDER-19){1'b0}}, 19'b1000000000000010011}; // 位5、位2、位1和位0反馈
            sequence_length = 32'd524287; // 2^19 - 1 = 524287
        end
        5'd9: begin // PN21: x^21 + x^2 + 1 (本原多项式)
            feedback_mask = {{(MAX_PN_ORDER-21){1'b0}}, 21'b100000000000000000100}; // 位2和位0反馈
            sequence_length = 32'd2097151; // 2^21 - 1 = 2097151
        end
        5'd10: begin // PN23: x^23 + x^5 + 1 (本原多项式)
            feedback_mask = {{(MAX_PN_ORDER-23){1'b0}}, 23'b10000000000000000010000}; // 位5和位0反馈
            sequence_length = 32'd8388607; // 2^23 - 1 = 8388607
        end
        5'd11: begin // PN25: x^25 + x^3 + 1 (本原多项式)
            feedback_mask = {{(MAX_PN_ORDER-25){1'b0}}, 25'b1000000000000000000000100}; // 位3和位0反馈
            sequence_length = 32'd33554431; // 2^25 - 1 = 33554431
        end
        5'd12: begin // PN27: x^27 + x^5 + x^2 + x + 1 (本原多项式)
            feedback_mask = {{(MAX_PN_ORDER-27){1'b0}}, 27'b100000000000000000000010011}; // 位5、位2、位1和位0反馈
            sequence_length = 32'd134217727; // 2^27 - 1 = 134217727
        end
        5'd13: begin // PN29: x^29 + x^2 + 1 (本原多项式)
            feedback_mask = {{(MAX_PN_ORDER-29){1'b0}}, 29'b10000000000000000000000000010}; // 位2和位0反馈
            sequence_length = 32'd536870911; // 2^29 - 1 = 536870911
        end
        5'd14: begin // PN31: x^31 + x^3 + 1 (本原多项式)
            feedback_mask = {{(MAX_PN_ORDER-31){1'b0}}, 31'b1000000000000000000000000000100}; // 位3和位0反馈
            sequence_length = 32'd2147483647; // 2^31 - 1 = 2147483647
        end
        default: begin // 默认使用PN3
            feedback_mask = {{(MAX_PN_ORDER-3){1'b0}}, 3'b011}; // 位1和位0反馈
            sequence_length = 32'd7; // 2^3 - 1 = 7
        end
    endcase
end

endmodule

Mine/prbs_core_lfsr_tb.v
`timescale 1ns / 1ps
//////////////////////////////////////////////////////////////////////////////////
// 模块名称: prbs_core_lfsr_tb
// 功能描述: PRBS核心生成器测试模块
//////////////////////////////////////////////////////////////////////////////////

module prbs_core_lfsr_tb();

// 时钟和复位信号
reg         dac_clk;
reg         reset_n;

// 控制信号
reg         lfsr_clk_enable;
reg [4:0]   prbs_pn_select_reg; // 0:PN3, 1:PN5, 2:PN7, 3:PN9, 4:PN11, 5:PN13, 6:PN15, 7:PN17, 8:PN19, 9:PN21, 10:PN23, 11:PN25, 12:PN27, 13:PN29, 14:PN31

// 输出信号
wire        prbs_bit_out;
wire        data_valid;
wire [32:0] lfsr_state;     // LFSR寄存器状态，用于调试

// 计数器和其他测试变量
integer     i;
integer     bit_count;
integer     one_count;
integer     zero_count;

// 被测试模块实例化
prbs_core_lfsr uut (
    .dac_clk(dac_clk),
    .reset_n(reset_n),
    .lfsr_clk_enable(lfsr_clk_enable),
    .prbs_pn_select_reg(prbs_pn_select_reg),
    .prbs_bit_out(prbs_bit_out),
    .data_valid(data_valid),
    .lfsr_state(lfsr_state)
);

// 时钟生成 - 625MHz的时钟周期为1.6ns
initial begin
    dac_clk = 0;
    forever #0.8 dac_clk = ~dac_clk; // 半周期0.8ns
end

// 测试过程
initial begin
    // 注册波形文件
    $dumpfile("prbs_core_lfsr_sim.vcd");
    $dumpvars(0, prbs_core_lfsr_tb);
    $display("Starting PRBS core LFSR simulation...");
    
    // 初始化
    reset_n = 0;
    lfsr_clk_enable = 0;
    prbs_pn_select_reg = 0; // 选择PN5序列
    bit_count = 0;
    one_count = 0;
    zero_count = 0;
    
    // 复位释放
    #10;
    reset_n = 1;
    #10;
    
    // 测试PN5序列
    $display("Testing PN5 sequence...");
    prbs_pn_select_reg = 'd1;
    
    // 生成100个PRBS位
    for (i = 0; i < 100; i = i + 1) begin
        lfsr_clk_enable = 1;
        #1.6; // 一个时钟周期
        lfsr_clk_enable = 0;
        #1.6; // 等待一个时钟周期
        
        // 统计输出
        bit_count = bit_count + 1;
        if (prbs_bit_out)
            one_count = one_count + 1;
        else
            zero_count = zero_count + 1;
        
        // 打印输出
        $display("Bit %d: PRBS=%b, Data Valid=%b, LFSR State=%b (Decimal=%d)", 
                 i, prbs_bit_out, data_valid, lfsr_state[4:0], lfsr_state[4:0]);
    end
    
    // 显示统计结果
    $display("PN5 Statistics: Total bits: %d, Ones: %d, Zeros: %d", bit_count, one_count, zero_count);
    
    // 观察PN5序列的完整周期
    $display("\nObserving complete PN5 sequence cycle...");
    $display("--------------------------------------------");
    $display("Clock | LFSR State | PRBS Output | Data Valid");
    $display("--------------------------------------------");
    
    // 重置并观察PN5的完整周期（应为31个状态）
    reset_n = 0;
    #10;
    reset_n = 1;
    #10;
    
    // 生成35个时钟周期，足够观察PN5的完整周期
    for (i = 0; i < 35; i = i + 1) begin
        $display("%4d | %b (%3d) | %b | %b", 
                 i, lfsr_state[4:0], lfsr_state[4:0], prbs_bit_out, data_valid);
        
        lfsr_clk_enable = 1;
        #1.6; // 一个时钟周期
        lfsr_clk_enable = 0;
        #1.6; // 等待一个时钟周期
    end
    
    $display("--------------------------------------------");
    $display("PN5 sequence cycle observation complete");
    
    // 结束仿真
    #10;
    $finish;
end

// 监视data_valid信号
always @(posedge data_valid) begin
    if (reset_n) begin
        $display("Time: %t, Sequence completed, PN type: %d", $time, prbs_pn_select_reg);
    end
end

endmodule

Mine/prbs_core_lfsr_sim.vcd
$date
	Fri May 30 15:11:33 2025
$end
$version
	Icarus Verilog
$end
$timescale
	1ps
$end
$scope module prbs_core_lfsr_tb $end
$var wire 1 ! prbs_bit_out $end
$var wire 33 " lfsr_state [32:0] $end
$var wire 1 # data_valid $end
$var reg 1 $ dac_clk $end
$var reg 1 % lfsr_clk_enable $end
$var reg 5 & prbs_pn_select_reg [4:0] $end
$var reg 1 ' reset_n $end
$var integer 32 ( bit_count [31:0] $end
$var integer 32 ) i [31:0] $end
$var integer 32 * one_count [31:0] $end
$var integer 32 + zero_count [31:0] $end
$scope module uut $end
$var wire 1 $ dac_clk $end
$var wire 1 % lfsr_clk_enable $end
$var wire 33 , lfsr_state [32:0] $end
$var wire 5 - prbs_pn_select_reg [4:0] $end
$var wire 1 ' reset_n $end
$var wire 1 . feedback_bit $end
$var parameter 32 / MAX_PN_ORDER $end
$var reg 32 0 bit_counter [31:0] $end
$var reg 1 # data_valid $end
$var reg 33 1 feedback_mask [32:0] $end
$var reg 33 2 lfsr_reg [32:0] $end
$var reg 1 ! prbs_bit_out $end
$var reg 32 3 sequence_length [31:0] $end
$upscope $end
$upscope $end
$enddefinitions $end
$comment Show the parameter values. $end
$dumpall
b100001 /
$end
#0
$dumpvars
b111 3
b1 2
b101 1
b0 0
1.
b0 -
b1 ,
b0 +
b0 *
bx )
b0 (
0'
b0 &
0%
0$
0#
b1 "
0!
$end
#800
1$
#1600
0$
#2400
1$
#3200
0$
#4000
1$
#4800
0$
#5600
1$
#6400
0$
#7200
1$
#8000
0$
#8800
1$
#9600
0$
#10000
1'
#10400
1$
#11200
0$
#12000
1$
#12800
0$
#13600
1$
#14400
0$
#15200
1$
#16000
0$
#16800
1$
#17600
0$
#18400
1$
#19200
0$
#20000
0.
b1 0
b10000 "
b10000 ,
b10000 2
b11111 3
b1001 1
1$
1%
b0 )
b1 &
b1 -
#20800
0$
#21600
1$
0%
#22400
0$
#23200
1.
b10 0
b1000 "
b1000 ,
b1000 2
1$
1%
b1 )
b1 +
b1 (
#24000
0$
#24800
1$
0%
#25600
0$
#26400
0.
b11 0
b10100 "
b10100 ,
b10100 2
1$
1%
b10 )
b10 +
b10 (
#27200
0$
#28000
1$
0%
#28800
0$
#29600
1.
b100 0
b1010 "
b1010 ,
b1010 2
1$
1%
b11 )
b11 +
b11 (
#30400
0$
#31200
1$
0%
#32000
0$
#32800
b101 0
b10101 "
b10101 ,
b10101 2
1$
1%
b100 )
b100 +
b100 (
#33600
0$
#34400
1$
0%
#35200
0$
#36000
b110 0
b11010 "
b11010 ,
b11010 2
1$
1%
b101 )
b101 +
b101 (
#36800
0$
#37600
1$
0%
#38400
0$
#39200
0.
b111 0
b11101 "
b11101 ,
b11101 2
1$
1%
b110 )
b110 +
b110 (
#40000
0$
#40800
1$
0%
#41600
0$
#42400
1.
b1000 0
b1110 "
b1110 ,
b1110 2
1$
1%
b111 )
b111 +
b111 (
#43200
0$
#44000
1$
0%
#44800
0$
#45600
b1001 0
b10111 "
b10111 ,
b10111 2
1$
1%
b1000 )
b1000 +
b1000 (
#46400
0$
#47200
1$
0%
#48000
0$
#48800
0.
b1010 0
b11011 "
b11011 ,
b11011 2
1$
1%
b1001 )
b1001 +
b1001 (
#49600
0$
#50400
1$
0%
#51200
0$
#52000
b1011 0
b1101 "
b1101 ,
b1101 2
1$
1%
b1010 )
b1010 +
b1010 (
#52800
0$
#53600
1$
0%
#54400
0$
#55200
b1100 0
b110 "
b110 ,
b110 2
1$
1%
b1011 )
b1011 +
b1011 (
#56000
0$
#56800
1$
0%
#57600
0$
#58400
1.
b1101 0
b11 "
b11 ,
b11 2
1$
1%
b1100 )
b1100 +
b1100 (
#59200
0$
#60000
1$
0%
#60800
0$
#61600
b1110 0
b10001 "
b10001 ,
b10001 2
1$
1%
b1101 )
b1101 +
b1101 (
#62400
0$
#63200
1$
0%
#64000
0$
#64800
b1111 0
b11000 "
b11000 ,
b11000 2
1$
1%
b1110 )
b1110 +
b1110 (
#65600
0$
#66400
1$
0%
#67200
0$
#68000
b10000 0
b11100 "
b11100 ,
b11100 2
1$
1%
b1111 )
b1111 +
b1111 (
#68800
0$
#69600
1$
0%
#70400
0$
#71200
b10001 0
b11110 "
b11110 ,
b11110 2
1$
1%
b10000 )
b10000 +
b10000 (
#72000
0$
#72800
1$
0%
#73600
0$
#74400
0.
b10010 0
b11111 "
b11111 ,
b11111 2
1$
1%
b10001 )
b10001 +
b10001 (
#75200
0$
#76000
1$
0%
#76800
0$
#77600
b10011 0
b1111 "
b1111 ,
b1111 2
1$
1%
b10010 )
b10010 +
b10010 (
#78400
0$
#79200
1$
0%
#80000
0$
#80800
1.
b10100 0
b111 "
b111 ,
b111 2
1$
1%
b10011 )
b10011 +
b10011 (
#81600
0$
#82400
1$
0%
#83200
0$
#84000
b10101 0
b10011 "
b10011 ,
b10011 2
1$
1%
b10100 )
b10100 +
b10100 (
#84800
0$
#85600
1$
0%
#86400
0$
#87200
0.
b10110 0
b11001 "
b11001 ,
b11001 2
1$
1%
b10101 )
b10101 +
b10101 (
#88000
0$
#88800
1$
0%
#89600
0$
#90400
1.
b10111 0
b1100 "
b1100 ,
b1100 2
1$
1%
b10110 )
b10110 +
b10110 (
#91200
0$
#92000
1$
0%
#92800
0$
#93600
0.
b11000 0
b10110 "
b10110 ,
b10110 2
1$
1%
b10111 )
b10111 +
b10111 (
#94400
0$
#95200
1$
0%
#96000
0$
#96800
b11001 0
b1011 "
b1011 ,
b1011 2
1$
1%
b11000 )
b11000 +
b11000 (
#97600
0$
#98400
1$
0%
#99200
0$
#100000
1.
b11010 0
b101 "
b101 ,
b101 2
1$
1%
b11001 )
b11001 +
b11001 (
#100800
0$
#101600
1$
0%
#102400
0$
#103200
0.
b11011 0
b10010 "
b10010 ,
b10010 2
1$
1%
b11010 )
b11010 +
b11010 (
#104000
0$
#104800
1$
0%
#105600
0$
#106400
b11100 0
b1001 "
b1001 ,
b1001 2
1$
1%
b11011 )
b11011 +
b11011 (
#107200
0$
#108000
1$
0%
#108800
0$
#109600
b11101 0
b100 "
b100 ,
b100 2
1$
1%
b11100 )
b11100 +
b11100 (
#110400
0$
#111200
1$
0%
#112000
0$
#112800
b11110 0
b10 "
b10 ,
b10 2
1$
1%
b11101 )
b11101 +
b11101 (
#113600
0$
#114400
1$
0%
#115200
0$
#116000
1.
1#
b0 0
b1 "
b1 ,
b1 2
1$
1%
b11110 )
b11110 +
b11110 (
#116800
0$
#117600
0#
1$
0%
#118400
0$
#119200
0.
b1 0
b10000 "
b10000 ,
b10000 2
1$
1%
b11111 )
b11111 +
b11111 (
#120000
0$
#120800
1$
0%
#121600
0$
#122400
1.
b10 0
b1000 "
b1000 ,
b1000 2
1$
1%
b100000 )
b100000 +
b100000 (
#123200
0$
#124000
1$
0%
#124800
0$
#125600
0.
b11 0
b10100 "
b10100 ,
b10100 2
1$
1%
b100001 )
b100001 +
b100001 (
#126400
0$
#127200
1$
0%
#128000
0$
#128800
1.
b100 0
b1010 "
b1010 ,
b1010 2
1$
1%
b100010 )
b100010 +
b100010 (
#129600
0$
#130400
1$
0%
#131200
0$
#132000
b101 0
b10101 "
b10101 ,
b10101 2
1$
1%
b100011 )
b100011 +
b100011 (
#132800
0$
#133600
1$
0%
#134400
0$
#135200
b110 0
b11010 "
b11010 ,
b11010 2
1$
1%
b100100 )
b100100 +
b100100 (
#136000
0$
#136800
1$
0%
#137600
0$
#138400
0.
b111 0
b11101 "
b11101 ,
b11101 2
1$
1%
b100101 )
b100101 +
b100101 (
#139200
0$
#140000
1$
0%
#140800
0$
#141600
1.
b1000 0
b1110 "
b1110 ,
b1110 2
1$
1%
b100110 )
b100110 +
b100110 (
#142400
0$
#143200
1$
0%
#144000
0$
#144800
b1001 0
b10111 "
b10111 ,
b10111 2
1$
1%
b100111 )
b100111 +
b100111 (
#145600
0$
#146400
1$
0%
#147200
0$
#148000
0.
b1010 0
b11011 "
b11011 ,
b11011 2
1$
1%
b101000 )
b101000 +
b101000 (
#148800
0$
#149600
1$
0%
#150400
0$
#151200
b1011 0
b1101 "
b1101 ,
b1101 2
1$
1%
b101001 )
b101001 +
b101001 (
#152000
0$
#152800
1$
0%
#153600
0$
#154400
b1100 0
b110 "
b110 ,
b110 2
1$
1%
b101010 )
b101010 +
b101010 (
#155200
0$
#156000
1$
0%
#156800
0$
#157600
1.
b1101 0
b11 "
b11 ,
b11 2
1$
1%
b101011 )
b101011 +
b101011 (
#158400
0$
#159200
1$
0%
#160000
0$
#160800
b1110 0
b10001 "
b10001 ,
b10001 2
1$
1%
b101100 )
b101100 +
b101100 (
#161600
0$
#162400
1$
0%
#163200
0$
#164000
b1111 0
b11000 "
b11000 ,
b11000 2
1$
1%
b101101 )
b101101 +
b101101 (
#164800
0$
#165600
1$
0%
#166400
0$
#167200
b10000 0
b11100 "
b11100 ,
b11100 2
1$
1%
b101110 )
b101110 +
b101110 (
#168000
0$
#168800
1$
0%
#169600
0$
#170400
b10001 0
b11110 "
b11110 ,
b11110 2
1$
1%
b101111 )
b101111 +
b101111 (
#171200
0$
#172000
1$
0%
#172800
0$
#173600
0.
b10010 0
b11111 "
b11111 ,
b11111 2
1$
1%
b110000 )
b110000 +
b110000 (
#174400
0$
#175200
1$
0%
#176000
0$
#176800
b10011 0
b1111 "
b1111 ,
b1111 2
1$
1%
b110001 )
b110001 +
b110001 (
#177600
0$
#178400
1$
0%
#179200
0$
#180000
1.
b10100 0
b111 "
b111 ,
b111 2
1$
1%
b110010 )
b110010 +
b110010 (
#180800
0$
#181600
1$
0%
#182400
0$
#183200
b10101 0
b10011 "
b10011 ,
b10011 2
1$
1%
b110011 )
b110011 +
b110011 (
#184000
0$
#184800
1$
0%
#185600
0$
#186400
0.
b10110 0
b11001 "
b11001 ,
b11001 2
1$
1%
b110100 )
b110100 +
b110100 (
#187200
0$
#188000
1$
0%
#188800
0$
#189600
1.
b10111 0
b1100 "
b1100 ,
b1100 2
1$
1%
b110101 )
b110101 +
b110101 (
#190400
0$
#191200
1$
0%
#192000
0$
#192800
0.
b11000 0
b10110 "
b10110 ,
b10110 2
1$
1%
b110110 )
b110110 +
b110110 (
#193600
0$
#194400
1$
0%
#195200
0$
#196000
b11001 0
b1011 "
b1011 ,
b1011 2
1$
1%
b110111 )
b110111 +
b110111 (
#196800
0$
#197600
1$
0%
#198400
0$
#199200
1.
b11010 0
b101 "
b101 ,
b101 2
1$
1%
b111000 )
b111000 +
b111000 (
#200000
0$
#200800
1$
0%
#201600
0$
#202400
0.
b11011 0
b10010 "
b10010 ,
b10010 2
1$
1%
b111001 )
b111001 +
b111001 (
#203200
0$
#204000
1$
0%
#204800
0$
#205600
b11100 0
b1001 "
b1001 ,
b1001 2
1$
1%
b111010 )
b111010 +
b111010 (
#206400
0$
#207200
1$
0%
#208000
0$
#208800
b11101 0
b100 "
b100 ,
b100 2
1$
1%
b111011 )
b111011 +
b111011 (
#209600
0$
#210400
1$
0%
#211200
0$
#212000
b11110 0
b10 "
b10 ,
b10 2
1$
1%
b111100 )
b111100 +
b111100 (
#212800
0$
#213600
1$
0%
#214400
0$
#215200
1.
1#
b0 0
b1 "
b1 ,
b1 2
1$
1%
b111101 )
b111101 +
b111101 (
#216000
0$
#216800
0#
1$
0%
#217600
0$
#218400
0.
b1 0
b10000 "
b10000 ,
b10000 2
1$
1%
b111110 )
b111110 +
b111110 (
#219200
0$
#220000
1$
0%
#220800
0$
#221600
1.
b10 0
b1000 "
b1000 ,
b1000 2
1$
1%
b111111 )
b111111 +
b111111 (
#222400
0$
#223200
1$
0%
#224000
0$
#224800
0.
b11 0
b10100 "
b10100 ,
b10100 2
1$
1%
b1000000 )
b1000000 +
b1000000 (
#225600
0$
#226400
1$
0%
#227200
0$
#228000
1.
b100 0
b1010 "
b1010 ,
b1010 2
1$
1%
b1000001 )
b1000001 +
b1000001 (
#228800
0$
#229600
1$
0%
#230400
0$
#231200
b101 0
b10101 "
b10101 ,
b10101 2
1$
1%
b1000010 )
b1000010 +
b1000010 (
#232000
0$
#232800
1$
0%
#233600
0$
#234400
b110 0
b11010 "
b11010 ,
b11010 2
1$
1%
b1000011 )
b1000011 +
b1000011 (
#235200
0$
#236000
1$
0%
#236800
0$
#237600
0.
b111 0
b11101 "
b11101 ,
b11101 2
1$
1%
b1000100 )
b1000100 +
b1000100 (
#238400
0$
#239200
1$
0%
#240000
0$
#240800
1.
b1000 0
b1110 "
b1110 ,
b1110 2
1$
1%
b1000101 )
b1000101 +
b1000101 (
#241600
0$
#242400
1$
0%
#243200
0$
#244000
b1001 0
b10111 "
b10111 ,
b10111 2
1$
1%
b1000110 )
b1000110 +
b1000110 (
#244800
0$
#245600
1$
0%
#246400
0$
#247200
0.
b1010 0
b11011 "
b11011 ,
b11011 2
1$
1%
b1000111 )
b1000111 +
b1000111 (
#248000
0$
#248800
1$
0%
#249600
0$
#250400
b1011 0
b1101 "
b1101 ,
b1101 2
1$
1%
b1001000 )
b1001000 +
b1001000 (
#251200
0$
#252000
1$
0%
#252800
0$
#253600
b1100 0
b110 "
b110 ,
b110 2
1$
1%
b1001001 )
b1001001 +
b1001001 (
#254400
0$
#255200
1$
0%
#256000
0$
#256800
1.
b1101 0
b11 "
b11 ,
b11 2
1$
1%
b1001010 )
b1001010 +
b1001010 (
#257600
0$
#258400
1$
0%
#259200
0$
#260000
b1110 0
b10001 "
b10001 ,
b10001 2
1$
1%
b1001011 )
b1001011 +
b1001011 (
#260800
0$
#261600
1$
0%
#262400
0$
#263200
b1111 0
b11000 "
b11000 ,
b11000 2
1$
1%
b1001100 )
b1001100 +
b1001100 (
#264000
0$
#264800
1$
0%
#265600
0$
#266400
b10000 0
b11100 "
b11100 ,
b11100 2
1$
1%
b1001101 )
b1001101 +
b1001101 (
#267200
0$
#268000
1$
0%
#268800
0$
#269600
b10001 0
b11110 "
b11110 ,
b11110 2
1$
1%
b1001110 )
b1001110 +
b1001110 (
#270400
0$
#271200
1$
0%
#272000
0$
#272800
0.
b10010 0
b11111 "
b11111 ,
b11111 2
1$
1%
b1001111 )
b1001111 +
b1001111 (
#273600
0$
#274400
1$
0%
#275200
0$
#276000
b10011 0
b1111 "
b1111 ,
b1111 2
1$
1%
b1010000 )
b1010000 +
b1010000 (
#276800
0$
#277600
1$
0%
#278400
0$
#279200
1.
b10100 0
b111 "
b111 ,
b111 2
1$
1%
b1010001 )
b1010001 +
b1010001 (
#280000
0$
#280800
1$
0%
#281600
0$
#282400
b10101 0
b10011 "
b10011 ,
b10011 2
1$
1%
b1010010 )
b1010010 +
b1010010 (
#283200
0$
#284000
1$
0%
#284800
0$
#285600
0.
b10110 0
b11001 "
b11001 ,
b11001 2
1$
1%
b1010011 )
b1010011 +
b1010011 (
#286400
0$
#287200
1$
0%
#288000
0$
#288800
1.
b10111 0
b1100 "
b1100 ,
b1100 2
1$
1%
b1010100 )
b1010100 +
b1010100 (
#289600
0$
#290400
1$
0%
#291200
0$
#292000
0.
b11000 0
b10110 "
b10110 ,
b10110 2
1$
1%
b1010101 )
b1010101 +
b1010101 (
#292800
0$
#293600
1$
0%
#294400
0$
#295200
b11001 0
b1011 "
b1011 ,
b1011 2
1$
1%
b1010110 )
b1010110 +
b1010110 (
#296000
0$
#296800
1$
0%
#297600
0$
#298400
1.
b11010 0
b101 "
b101 ,
b101 2
1$
1%
b1010111 )
b1010111 +
b1010111 (
#299200
0$
#300000
1$
0%
#300800
0$
#301600
0.
b11011 0
b10010 "
b10010 ,
b10010 2
1$
1%
b1011000 )
b1011000 +
b1011000 (
#302400
0$
#303200
1$
0%
#304000
0$
#304800
b11100 0
b1001 "
b1001 ,
b1001 2
1$
1%
b1011001 )
b1011001 +
b1011001 (
#305600
0$
#306400
1$
0%
#307200
0$
#308000
b11101 0
b100 "
b100 ,
b100 2
1$
1%
b1011010 )
b1011010 +
b1011010 (
#308800
0$
#309600
1$
0%
#310400
0$
#311200
b11110 0
b10 "
b10 ,
b10 2
1$
1%
b1011011 )
b1011011 +
b1011011 (
#312000
0$
#312800
1$
0%
#313600
0$
#314400
1.
1#
b0 0
b1 "
b1 ,
b1 2
1$
1%
b1011100 )
b1011100 +
b1011100 (
#315200
0$
#316000
0#
1$
0%
#316800
0$
#317600
0.
b1 0
b10000 "
b10000 ,
b10000 2
1$
1%
b1011101 )
b1011101 +
b1011101 (
#318400
0$
#319200
1$
0%
#320000
0$
#320800
1.
b10 0
b1000 "
b1000 ,
b1000 2
1$
1%
b1011110 )
b1011110 +
b1011110 (
